<?xml version="1.0" encoding="UTF-8"?>
<DailyXpHighscores>
  <GeneratedAt>1746206733157</GeneratedAt>
  <Player>
    <Rank>1</Rank>
    <Name>Papito</Name>
    <XpEarned>507103427</XpEarned>
  </Player>
  <Player>
    <Rank>2</Rank>
    <Name>Hiroshi</Name>
    <XpEarned>406110289</XpEarned>
  </Player>
  <Player>
    <Rank>3</Rank>
    <Name>Frieren</Name>
    <XpEarned>322464118</XpEarned>
  </Player>
  <Player>
    <Rank>4</Rank>
    <Name>Existence</Name>
    <XpEarned>276841889</XpEarned>
  </Player>
  <Player>
    <Rank>5</Rank>
    <Name>Cimit</Name>
    <XpEarned>242664578</XpEarned>
  </Player>
  <Player>
    <Rank>6</Rank>
    <Name>Kakashi</Name>
    <XpEarned>230365706</XpEarned>
  </Player>
  <Player>
    <Rank>7</Rank>
    <Name>Dom</Name>
    <XpEarned>177034872</XpEarned>
  </Player>
  <Player>
    <Rank>8</Rank>
    <Name>Tec</Name>
    <XpEarned>163339523</XpEarned>
  </Player>
  <Player>
    <Rank>9</Rank>
    <Name>Kingeddi</Name>
    <XpEarned>150383575</XpEarned>
  </Player>
  <Player>
    <Rank>10</Rank>
    <Name>Acayhere</Name>
    <XpEarned>145372345</XpEarned>
  </Player>
  <Player>
    <Rank>11</Rank>
    <Name>Warr</Name>
    <XpEarned>141523510</XpEarned>
  </Player>
  <Player>
    <Rank>12</Rank>
    <Name>Kannibalz</Name>
    <XpEarned>135219744</XpEarned>
  </Player>
  <Player>
    <Rank>13</Rank>
    <Name>Wk</Name>
    <XpEarned>124266614</XpEarned>
  </Player>
  <Player>
    <Rank>14</Rank>
    <Name>Kingdeus</Name>
    <XpEarned>118194878</XpEarned>
  </Player>
  <Player>
    <Rank>15</Rank>
    <Name>Mahadewa</Name>
    <XpEarned>111522509</XpEarned>
  </Player>
  <Player>
    <Rank>16</Rank>
    <Name>Papasmerf</Name>
    <XpEarned>111156080</XpEarned>
  </Player>
  <Player>
    <Rank>17</Rank>
    <Name>Connor</Name>
    <XpEarned>107754225</XpEarned>
  </Player>
  <Player>
    <Rank>18</Rank>
    <Name>Pancernik</Name>
    <XpEarned>106804221</XpEarned>
  </Player>
  <Player>
    <Rank>19</Rank>
    <Name>Rog</Name>
    <XpEarned>103081712</XpEarned>
  </Player>
  <Player>
    <Rank>20</Rank>
    <Name>Lendario</Name>
    <XpEarned>97160682</XpEarned>
  </Player>
  <Player>
    <Rank>21</Rank>
    <Name>Harun</Name>
    <XpEarned>95742137</XpEarned>
  </Player>
  <Player>
    <Rank>22</Rank>
    <Name>Templarr</Name>
    <XpEarned>91369081</XpEarned>
  </Player>
  <Player>
    <Rank>23</Rank>
    <Name>Calla</Name>
    <XpEarned>86526895</XpEarned>
  </Player>
  <Player>
    <Rank>24</Rank>
    <Name>Victorbr</Name>
    <XpEarned>79815324</XpEarned>
  </Player>
  <Player>
    <Rank>25</Rank>
    <Name>Zezie</Name>
    <XpEarned>79477736</XpEarned>
  </Player>
  <Player>
    <Rank>26</Rank>
    <Name>Barba</Name>
    <XpEarned>77184537</XpEarned>
  </Player>
  <Player>
    <Rank>27</Rank>
    <Name>Aifa</Name>
    <XpEarned>75722450</XpEarned>
  </Player>
  <Player>
    <Rank>28</Rank>
    <Name>Johnnywar</Name>
    <XpEarned>74964923</XpEarned>
  </Player>
  <Player>
    <Rank>29</Rank>
    <Name>Crsytal</Name>
    <XpEarned>73022620</XpEarned>
  </Player>
  <Player>
    <Rank>30</Rank>
    <Name>Ynk</Name>
    <XpEarned>72641201</XpEarned>
  </Player>
  <Player>
    <Rank>31</Rank>
    <Name>Psychomage</Name>
    <XpEarned>71807866</XpEarned>
  </Player>
  <Player>
    <Rank>32</Rank>
    <Name>Connorz</Name>
    <XpEarned>71335872</XpEarned>
  </Player>
  <Player>
    <Rank>33</Rank>
    <Name>Stella</Name>
    <XpEarned>68572301</XpEarned>
  </Player>
  <Player>
    <Rank>34</Rank>
    <Name>Killer </Name>
    <XpEarned>68412943</XpEarned>
  </Player>
  <Player>
    <Rank>35</Rank>
    <Name>Techno</Name>
    <XpEarned>66868214</XpEarned>
  </Player>
  <Player>
    <Rank>36</Rank>
    <Name>Mineiro</Name>
    <XpEarned>65560898</XpEarned>
  </Player>
  <Player>
    <Rank>37</Rank>
    <Name>Templar</Name>
    <XpEarned>63529558</XpEarned>
  </Player>
  <Player>
    <Rank>38</Rank>
    <Name>Willinha </Name>
    <XpEarned>62582348</XpEarned>
  </Player>
  <Player>
    <Rank>39</Rank>
    <Name>Mineira</Name>
    <XpEarned>61413815</XpEarned>
  </Player>
  <Player>
    <Rank>40</Rank>
    <Name>Kingkiller</Name>
    <XpEarned>61177167</XpEarned>
  </Player>
  <Player>
    <Rank>41</Rank>
    <Name>Heineken</Name>
    <XpEarned>60019962</XpEarned>
  </Player>
  <Player>
    <Rank>42</Rank>
    <Name>Justen</Name>
    <XpEarned>58951149</XpEarned>
  </Player>
  <Player>
    <Rank>43</Rank>
    <Name>Chifuyu</Name>
    <XpEarned>58590784</XpEarned>
  </Player>
  <Player>
    <Rank>44</Rank>
    <Name>Hellwizz</Name>
    <XpEarned>56533297</XpEarned>
  </Player>
  <Player>
    <Rank>45</Rank>
    <Name>Wiillmk</Name>
    <XpEarned>55004596</XpEarned>
  </Player>
  <Player>
    <Rank>46</Rank>
    <Name>Lou</Name>
    <XpEarned>54374659</XpEarned>
  </Player>
  <Player>
    <Rank>47</Rank>
    <Name>Zedalapa</Name>
    <XpEarned>51329509</XpEarned>
  </Player>
  <Player>
    <Rank>48</Rank>
    <Name>Ashura</Name>
    <XpEarned>51238543</XpEarned>
  </Player>
  <Player>
    <Rank>49</Rank>
    <Name>Justin</Name>
    <XpEarned>51097994</XpEarned>
  </Player>
  <Player>
    <Rank>50</Rank>
    <Name>Troyn</Name>
    <XpEarned>48424314</XpEarned>
  </Player>
  <Player>
    <Rank>51</Rank>
    <Name>Ironman</Name>
    <XpEarned>48354309</XpEarned>
  </Player>
  <Player>
    <Rank>52</Rank>
    <Name>Maxxbrr</Name>
    <XpEarned>46744859</XpEarned>
  </Player>
  <Player>
    <Rank>53</Rank>
    <Name>Kibo</Name>
    <XpEarned>44658173</XpEarned>
  </Player>
  <Player>
    <Rank>54</Rank>
    <Name>Mitt</Name>
    <XpEarned>44093001</XpEarned>
  </Player>
  <Player>
    <Rank>55</Rank>
    <Name>Yakoebom</Name>
    <XpEarned>41386350</XpEarned>
  </Player>
  <Player>
    <Rank>56</Rank>
    <Name>Fiolu</Name>
    <XpEarned>41052697</XpEarned>
  </Player>
  <Player>
    <Rank>57</Rank>
    <Name>Naruto</Name>
    <XpEarned>40340006</XpEarned>
  </Player>
  <Player>
    <Rank>58</Rank>
    <Name>Madara</Name>
    <XpEarned>39167794</XpEarned>
  </Player>
  <Player>
    <Rank>59</Rank>
    <Name>Hellokitty</Name>
    <XpEarned>38421370</XpEarned>
  </Player>
  <Player>
    <Rank>60</Rank>
    <Name>Jke</Name>
    <XpEarned>37258537</XpEarned>
  </Player>
  <Player>
    <Rank>61</Rank>
    <Name>Bruxo</Name>
    <XpEarned>36539997</XpEarned>
  </Player>
  <Player>
    <Rank>62</Rank>
    <Name>Meeca</Name>
    <XpEarned>36030035</XpEarned>
  </Player>
  <Player>
    <Rank>63</Rank>
    <Name>Wizzard</Name>
    <XpEarned>33641251</XpEarned>
  </Player>
  <Player>
    <Rank>64</Rank>
    <Name>Kinghorr</Name>
    <XpEarned>33402882</XpEarned>
  </Player>
  <Player>
    <Rank>65</Rank>
    <Name>Goldtanker</Name>
    <XpEarned>32927553</XpEarned>
  </Player>
  <Player>
    <Rank>66</Rank>
    <Name>Liliks</Name>
    <XpEarned>32808482</XpEarned>
  </Player>
  <Player>
    <Rank>67</Rank>
    <Name>Killerwiz</Name>
    <XpEarned>31939456</XpEarned>
  </Player>
  <Player>
    <Rank>68</Rank>
    <Name>Digdin</Name>
    <XpEarned>31491560</XpEarned>
  </Player>
  <Player>
    <Rank>69</Rank>
    <Name>Piras</Name>
    <XpEarned>30977809</XpEarned>
  </Player>
  <Player>
    <Rank>70</Rank>
    <Name>Panda</Name>
    <XpEarned>26283046</XpEarned>
  </Player>
  <Player>
    <Rank>71</Rank>
    <Name>Shizuka</Name>
    <XpEarned>25430703</XpEarned>
  </Player>
  <Player>
    <Rank>72</Rank>
    <Name>Pandatank</Name>
    <XpEarned>22613658</XpEarned>
  </Player>
  <Player>
    <Rank>73</Rank>
    <Name>Biel</Name>
    <XpEarned>22581875</XpEarned>
  </Player>
  <Player>
    <Rank>74</Rank>
    <Name>Vamplod</Name>
    <XpEarned>22502563</XpEarned>
  </Player>
  <Player>
    <Rank>75</Rank>
    <Name>Arthurktt</Name>
    <XpEarned>22022108</XpEarned>
  </Player>
  <Player>
    <Rank>76</Rank>
    <Name>Jeff</Name>
    <XpEarned>20735426</XpEarned>
  </Player>
  <Player>
    <Rank>77</Rank>
    <Name>Trovao</Name>
    <XpEarned>20209821</XpEarned>
  </Player>
  <Player>
    <Rank>78</Rank>
    <Name>Pintoral</Name>
    <XpEarned>19795507</XpEarned>
  </Player>
  <Player>
    <Rank>79</Rank>
    <Name>Lorenna</Name>
    <XpEarned>19593596</XpEarned>
  </Player>
  <Player>
    <Rank>80</Rank>
    <Name>Shanksz</Name>
    <XpEarned>19496660</XpEarned>
  </Player>
  <Player>
    <Rank>81</Rank>
    <Name>Ganny</Name>
    <XpEarned>17927890</XpEarned>
  </Player>
  <Player>
    <Rank>82</Rank>
    <Name>Snoww</Name>
    <XpEarned>17734124</XpEarned>
  </Player>
  <Player>
    <Rank>83</Rank>
    <Name>Sugar</Name>
    <XpEarned>17595124</XpEarned>
  </Player>
  <Player>
    <Rank>84</Rank>
    <Name>Megume</Name>
    <XpEarned>17531185</XpEarned>
  </Player>
  <Player>
    <Rank>85</Rank>
    <Name>Kaitt</Name>
    <XpEarned>17272776</XpEarned>
  </Player>
  <Player>
    <Rank>86</Rank>
    <Name>Giraya</Name>
    <XpEarned>17236125</XpEarned>
  </Player>
  <Player>
    <Rank>87</Rank>
    <Name>Rodrigues</Name>
    <XpEarned>17218551</XpEarned>
  </Player>
  <Player>
    <Rank>88</Rank>
    <Name>Aa</Name>
    <XpEarned>17011260</XpEarned>
  </Player>
  <Player>
    <Rank>89</Rank>
    <Name>Lendaria</Name>
    <XpEarned>16384162</XpEarned>
  </Player>
  <Player>
    <Rank>90</Rank>
    <Name>Afk</Name>
    <XpEarned>16216238</XpEarned>
  </Player>
  <Player>
    <Rank>91</Rank>
    <Name>Menson</Name>
    <XpEarned>16033187</XpEarned>
  </Player>
  <Player>
    <Rank>92</Rank>
    <Name>Destino</Name>
    <XpEarned>15838625</XpEarned>
  </Player>
  <Player>
    <Rank>93</Rank>
    <Name>Shaz</Name>
    <XpEarned>15467931</XpEarned>
  </Player>
  <Player>
    <Rank>94</Rank>
    <Name>Hellwilzz</Name>
    <XpEarned>15355547</XpEarned>
  </Player>
  <Player>
    <Rank>95</Rank>
    <Name>Baam</Name>
    <XpEarned>14841070</XpEarned>
  </Player>
  <Player>
    <Rank>96</Rank>
    <Name>Layse</Name>
    <XpEarned>14756140</XpEarned>
  </Player>
  <Player>
    <Rank>97</Rank>
    <Name>Srlira</Name>
    <XpEarned>14733697</XpEarned>
  </Player>
  <Player>
    <Rank>98</Rank>
    <Name>Maxxbr</Name>
    <XpEarned>14528969</XpEarned>
  </Player>
  <Player>
    <Rank>99</Rank>
    <Name>Alfisyeh</Name>
    <XpEarned>14439676</XpEarned>
  </Player>
  <Player>
    <Rank>100</Rank>
    <Name>Dressrossa</Name>
    <XpEarned>13699630</XpEarned>
  </Player>
  <Player>
    <Rank>101</Rank>
    <Name>Xxfuxx</Name>
    <XpEarned>13017972</XpEarned>
  </Player>
  <Player>
    <Rank>102</Rank>
    <Name>Mit</Name>
    <XpEarned>12977257</XpEarned>
  </Player>
  <Player>
    <Rank>103</Rank>
    <Name>Shadowww</Name>
    <XpEarned>12955847</XpEarned>
  </Player>
  <Player>
    <Rank>104</Rank>
    <Name>Nibda</Name>
    <XpEarned>12850636</XpEarned>
  </Player>
  <Player>
    <Rank>105</Rank>
    <Name>Scott</Name>
    <XpEarned>12711836</XpEarned>
  </Player>
  <Player>
    <Rank>106</Rank>
    <Name>Infor</Name>
    <XpEarned>12538680</XpEarned>
  </Player>
  <Player>
    <Rank>107</Rank>
    <Name>Gaspar</Name>
    <XpEarned>11832941</XpEarned>
  </Player>
  <Player>
    <Rank>108</Rank>
    <Name>Snob</Name>
    <XpEarned>11633404</XpEarned>
  </Player>
  <Player>
    <Rank>109</Rank>
    <Name>Zahard</Name>
    <XpEarned>11536405</XpEarned>
  </Player>
  <Player>
    <Rank>110</Rank>
    <Name>Klng</Name>
    <XpEarned>11098261</XpEarned>
  </Player>
  <Player>
    <Rank>111</Rank>
    <Name>Guard</Name>
    <XpEarned>11033518</XpEarned>
  </Player>
  <Player>
    <Rank>112</Rank>
    <Name>Kannisword</Name>
    <XpEarned>10682093</XpEarned>
  </Player>
  <Player>
    <Rank>113</Rank>
    <Name>Movie</Name>
    <XpEarned>10321402</XpEarned>
  </Player>
  <Player>
    <Rank>114</Rank>
    <Name>Ria</Name>
    <XpEarned>9775676</XpEarned>
  </Player>
  <Player>
    <Rank>115</Rank>
    <Name>Indra</Name>
    <XpEarned>9720558</XpEarned>
  </Player>
  <Player>
    <Rank>116</Rank>
    <Name>Blindadu</Name>
    <XpEarned>8892571</XpEarned>
  </Player>
  <Player>
    <Rank>117</Rank>
    <Name>Piraswiz</Name>
    <XpEarned>8830351</XpEarned>
  </Player>
  <Player>
    <Rank>118</Rank>
    <Name>Kannivrau</Name>
    <XpEarned>8764676</XpEarned>
  </Player>
  <Player>
    <Rank>119</Rank>
    <Name>Quince</Name>
    <XpEarned>8715487</XpEarned>
  </Player>
  <Player>
    <Rank>120</Rank>
    <Name>Buca</Name>
    <XpEarned>8511196</XpEarned>
  </Player>
  <Player>
    <Rank>121</Rank>
    <Name>Bsdeadpool</Name>
    <XpEarned>8139049</XpEarned>
  </Player>
  <Player>
    <Rank>122</Rank>
    <Name>Boos</Name>
    <XpEarned>7982718</XpEarned>
  </Player>
  <Player>
    <Rank>123</Rank>
    <Name>Khersek</Name>
    <XpEarned>7759413</XpEarned>
  </Player>
  <Player>
    <Rank>124</Rank>
    <Name>Dark</Name>
    <XpEarned>7719198</XpEarned>
  </Player>
  <Player>
    <Rank>125</Rank>
    <Name>Atheuz</Name>
    <XpEarned>7441019</XpEarned>
  </Player>
  <Player>
    <Rank>126</Rank>
    <Name>Eunha</Name>
    <XpEarned>7154996</XpEarned>
  </Player>
  <Player>
    <Rank>127</Rank>
    <Name>Ghost</Name>
    <XpEarned>6596811</XpEarned>
  </Player>
  <Player>
    <Rank>128</Rank>
    <Name>Noia</Name>
    <XpEarned>6378423</XpEarned>
  </Player>
  <Player>
    <Rank>129</Rank>
    <Name>Powerofgod</Name>
    <XpEarned>5794503</XpEarned>
  </Player>
  <Player>
    <Rank>130</Rank>
    <Name>Guardian</Name>
    <XpEarned>5751347</XpEarned>
  </Player>
  <Player>
    <Rank>131</Rank>
    <Name>Michael</Name>
    <XpEarned>5536933</XpEarned>
  </Player>
  <Player>
    <Rank>132</Rank>
    <Name>Ldakira</Name>
    <XpEarned>5377903</XpEarned>
  </Player>
  <Player>
    <Rank>133</Rank>
    <Name>Kazu</Name>
    <XpEarned>5203133</XpEarned>
  </Player>
  <Player>
    <Rank>134</Rank>
    <Name>Vendendo</Name>
    <XpEarned>5193099</XpEarned>
  </Player>
  <Player>
    <Rank>135</Rank>
    <Name>Kingsblack</Name>
    <XpEarned>5063471</XpEarned>
  </Player>
  <Player>
    <Rank>136</Rank>
    <Name>Kirito</Name>
    <XpEarned>4981340</XpEarned>
  </Player>
  <Player>
    <Rank>137</Rank>
    <Name>Kalea</Name>
    <XpEarned>4838764</XpEarned>
  </Player>
  <Player>
    <Rank>138</Rank>
    <Name>Gryffindor</Name>
    <XpEarned>4750000</XpEarned>
  </Player>
  <Player>
    <Rank>139</Rank>
    <Name>Opah</Name>
    <XpEarned>4750000</XpEarned>
  </Player>
  <Player>
    <Rank>140</Rank>
    <Name>Yuumi</Name>
    <XpEarned>4560267</XpEarned>
  </Player>
  <Player>
    <Rank>141</Rank>
    <Name>Canix</Name>
    <XpEarned>4333574</XpEarned>
  </Player>
  <Player>
    <Rank>142</Rank>
    <Name>Darsixer</Name>
    <XpEarned>4156841</XpEarned>
  </Player>
  <Player>
    <Rank>143</Rank>
    <Name>Fuva</Name>
    <XpEarned>4126923</XpEarned>
  </Player>
  <Player>
    <Rank>144</Rank>
    <Name>Rokz</Name>
    <XpEarned>4040989</XpEarned>
  </Player>
  <Player>
    <Rank>145</Rank>
    <Name>Valkiria</Name>
    <XpEarned>3969287</XpEarned>
  </Player>
  <Player>
    <Rank>146</Rank>
    <Name>Meliodas</Name>
    <XpEarned>3909575</XpEarned>
  </Player>
  <Player>
    <Rank>147</Rank>
    <Name>Sonk</Name>
    <XpEarned>3846541</XpEarned>
  </Player>
  <Player>
    <Rank>148</Rank>
    <Name>Dewezz</Name>
    <XpEarned>3780993</XpEarned>
  </Player>
  <Player>
    <Rank>149</Rank>
    <Name>Omadara</Name>
    <XpEarned>3664322</XpEarned>
  </Player>
  <Player>
    <Rank>150</Rank>
    <Name>Laxus</Name>
    <XpEarned>3535424</XpEarned>
  </Player>
  <Player>
    <Rank>151</Rank>
    <Name>Dewez</Name>
    <XpEarned>3353476</XpEarned>
  </Player>
  <Player>
    <Rank>152</Rank>
    <Name>Babydoll</Name>
    <XpEarned>3299753</XpEarned>
  </Player>
  <Player>
    <Rank>153</Rank>
    <Name>Magicol</Name>
    <XpEarned>3262607</XpEarned>
  </Player>
  <Player>
    <Rank>154</Rank>
    <Name>Magrela</Name>
    <XpEarned>3201627</XpEarned>
  </Player>
  <Player>
    <Rank>155</Rank>
    <Name>Tadalinha</Name>
    <XpEarned>2903213</XpEarned>
  </Player>
  <Player>
    <Rank>156</Rank>
    <Name>Vathar</Name>
    <XpEarned>2764751</XpEarned>
  </Player>
  <Player>
    <Rank>157</Rank>
    <Name>Hero</Name>
    <XpEarned>2721745</XpEarned>
  </Player>
  <Player>
    <Rank>158</Rank>
    <Name>Jcl</Name>
    <XpEarned>2553177</XpEarned>
  </Player>
  <Player>
    <Rank>159</Rank>
    <Name>Dewi</Name>
    <XpEarned>2432966</XpEarned>
  </Player>
  <Player>
    <Rank>160</Rank>
    <Name>Zetabaco</Name>
    <XpEarned>2399343</XpEarned>
  </Player>
  <Player>
    <Rank>161</Rank>
    <Name>Kaisel</Name>
    <XpEarned>2391711</XpEarned>
  </Player>
  <Player>
    <Rank>162</Rank>
    <Name>Salamaleko</Name>
    <XpEarned>2301916</XpEarned>
  </Player>
  <Player>
    <Rank>163</Rank>
    <Name>Cupy</Name>
    <XpEarned>2227860</XpEarned>
  </Player>
  <Player>
    <Rank>164</Rank>
    <Name>Rendezvous</Name>
    <XpEarned>2121878</XpEarned>
  </Player>
  <Player>
    <Rank>165</Rank>
    <Name>Narack</Name>
    <XpEarned>2044664</XpEarned>
  </Player>
  <Player>
    <Rank>166</Rank>
    <Name>Minitadala</Name>
    <XpEarned>2030605</XpEarned>
  </Player>
  <Player>
    <Rank>167</Rank>
    <Name>Bebelaq</Name>
    <XpEarned>2014196</XpEarned>
  </Player>
  <Player>
    <Rank>168</Rank>
    <Name>Jembuff</Name>
    <XpEarned>1979426</XpEarned>
  </Player>
  <Player>
    <Rank>169</Rank>
    <Name>Yuan</Name>
    <XpEarned>1951779</XpEarned>
  </Player>
  <Player>
    <Rank>170</Rank>
    <Name>Terceu</Name>
    <XpEarned>1900000</XpEarned>
  </Player>
  <Player>
    <Rank>171</Rank>
    <Name>Guinny</Name>
    <XpEarned>1756920</XpEarned>
  </Player>
  <Player>
    <Rank>172</Rank>
    <Name>Rigger</Name>
    <XpEarned>1728630</XpEarned>
  </Player>
  <Player>
    <Rank>173</Rank>
    <Name>Feiticeira</Name>
    <XpEarned>1578013</XpEarned>
  </Player>
  <Player>
    <Rank>174</Rank>
    <Name>Yakoeruim</Name>
    <XpEarned>1459766</XpEarned>
  </Player>
  <Player>
    <Rank>175</Rank>
    <Name>Villain</Name>
    <XpEarned>1439562</XpEarned>
  </Player>
  <Player>
    <Rank>176</Rank>
    <Name>Pingulinn</Name>
    <XpEarned>1426085</XpEarned>
  </Player>
  <Player>
    <Rank>177</Rank>
    <Name>Alegria</Name>
    <XpEarned>1370401</XpEarned>
  </Player>
  <Player>
    <Rank>178</Rank>
    <Name>Pageone</Name>
    <XpEarned>1354227</XpEarned>
  </Player>
  <Player>
    <Rank>179</Rank>
    <Name>Crystal</Name>
    <XpEarned>1300880</XpEarned>
  </Player>
  <Player>
    <Rank>180</Rank>
    <Name>Cosmos</Name>
    <XpEarned>1246457</XpEarned>
  </Player>
  <Player>
    <Rank>181</Rank>
    <Name>Bucca</Name>
    <XpEarned>1184523</XpEarned>
  </Player>
  <Player>
    <Rank>182</Rank>
    <Name>Judith</Name>
    <XpEarned>1137476</XpEarned>
  </Player>
  <Player>
    <Rank>183</Rank>
    <Name>Magus</Name>
    <XpEarned>1127588</XpEarned>
  </Player>
  <Player>
    <Rank>184</Rank>
    <Name>Spellwiz</Name>
    <XpEarned>1106866</XpEarned>
  </Player>
  <Player>
    <Rank>185</Rank>
    <Name>Garoto</Name>
    <XpEarned>1051145</XpEarned>
  </Player>
  <Player>
    <Rank>186</Rank>
    <Name>Lelekowl</Name>
    <XpEarned>1028732</XpEarned>
  </Player>
  <Player>
    <Rank>187</Rank>
    <Name>Gacorrr</Name>
    <XpEarned>1007061</XpEarned>
  </Player>
  <Player>
    <Rank>188</Rank>
    <Name>Ket</Name>
    <XpEarned>1002025</XpEarned>
  </Player>
  <Player>
    <Rank>189</Rank>
    <Name>Triad</Name>
    <XpEarned>950000</XpEarned>
  </Player>
  <Player>
    <Rank>190</Rank>
    <Name>Buccca</Name>
    <XpEarned>950000</XpEarned>
  </Player>
  <Player>
    <Rank>191</Rank>
    <Name>Bucccca</Name>
    <XpEarned>950000</XpEarned>
  </Player>
  <Player>
    <Rank>192</Rank>
    <Name>Reheli</Name>
    <XpEarned>900900</XpEarned>
  </Player>
  <Player>
    <Rank>193</Rank>
    <Name>Fullwiz</Name>
    <XpEarned>888703</XpEarned>
  </Player>
  <Player>
    <Rank>194</Rank>
    <Name>Dewes</Name>
    <XpEarned>808522</XpEarned>
  </Player>
  <Player>
    <Rank>195</Rank>
    <Name>Warmega</Name>
    <XpEarned>781375</XpEarned>
  </Player>
  <Player>
    <Rank>196</Rank>
    <Name>Joe</Name>
    <XpEarned>757099</XpEarned>
  </Player>
  <Player>
    <Rank>197</Rank>
    <Name>Kingtibia</Name>
    <XpEarned>757080</XpEarned>
  </Player>
  <Player>
    <Rank>198</Rank>
    <Name>Yakuza</Name>
    <XpEarned>713620</XpEarned>
  </Player>
  <Player>
    <Rank>199</Rank>
    <Name>Somnus</Name>
    <XpEarned>648422</XpEarned>
  </Player>
  <Player>
    <Rank>200</Rank>
    <Name>Redzin</Name>
    <XpEarned>542430</XpEarned>
  </Player>
  <Player>
    <Rank>201</Rank>
    <Name>Nauk</Name>
    <XpEarned>484619</XpEarned>
  </Player>
  <Player>
    <Rank>202</Rank>
    <Name>Nena</Name>
    <XpEarned>475175</XpEarned>
  </Player>
  <Player>
    <Rank>203</Rank>
    <Name>Otto</Name>
    <XpEarned>475000</XpEarned>
  </Player>
  <Player>
    <Rank>204</Rank>
    <Name>Mnhoulisu</Name>
    <XpEarned>442488</XpEarned>
  </Player>
  <Player>
    <Rank>205</Rank>
    <Name>Shiroe</Name>
    <XpEarned>429320</XpEarned>
  </Player>
  <Player>
    <Rank>206</Rank>
    <Name>Willinha</Name>
    <XpEarned>410653</XpEarned>
  </Player>
  <Player>
    <Rank>207</Rank>
    <Name>Rossar</Name>
    <XpEarned>357702</XpEarned>
  </Player>
  <Player>
    <Rank>208</Rank>
    <Name>Spellwiz </Name>
    <XpEarned>328852</XpEarned>
  </Player>
  <Player>
    <Rank>209</Rank>
    <Name>Ekzim</Name>
    <XpEarned>322932</XpEarned>
  </Player>
  <Player>
    <Rank>210</Rank>
    <Name>Agenmarini</Name>
    <XpEarned>320961</XpEarned>
  </Player>
  <Player>
    <Rank>211</Rank>
    <Name>Skyblue</Name>
    <XpEarned>287424</XpEarned>
  </Player>
  <Player>
    <Rank>212</Rank>
    <Name>Johnnywiz </Name>
    <XpEarned>255732</XpEarned>
  </Player>
  <Player>
    <Rank>213</Rank>
    <Name>Sadness</Name>
    <XpEarned>236606</XpEarned>
  </Player>
  <Player>
    <Rank>214</Rank>
    <Name>Megume </Name>
    <XpEarned>191296</XpEarned>
  </Player>
  <Player>
    <Rank>215</Rank>
    <Name>Hamura</Name>
    <XpEarned>188848</XpEarned>
  </Player>
  <Player>
    <Rank>216</Rank>
    <Name>Wizav</Name>
    <XpEarned>188310</XpEarned>
  </Player>
  <Player>
    <Rank>217</Rank>
    <Name>Masterwiz</Name>
    <XpEarned>174860</XpEarned>
  </Player>
  <Player>
    <Rank>218</Rank>
    <Name>Frostfenix</Name>
    <XpEarned>173142</XpEarned>
  </Player>
  <Player>
    <Rank>219</Rank>
    <Name>Blor</Name>
    <XpEarned>139487</XpEarned>
  </Player>
  <Player>
    <Rank>220</Rank>
    <Name>Trapaceiro</Name>
    <XpEarned>131106</XpEarned>
  </Player>
  <Player>
    <Rank>221</Rank>
    <Name>Sandra</Name>
    <XpEarned>125811</XpEarned>
  </Player>
  <Player>
    <Rank>222</Rank>
    <Name>Kila</Name>
    <XpEarned>95264</XpEarned>
  </Player>
  <Player>
    <Rank>223</Rank>
    <Name>Kingbogu</Name>
    <XpEarned>68684</XpEarned>
  </Player>
  <Player>
    <Rank>224</Rank>
    <Name>Silentkill</Name>
    <XpEarned>56350</XpEarned>
  </Player>
  <Player>
    <Rank>225</Rank>
    <Name>Mael</Name>
    <XpEarned>36189</XpEarned>
  </Player>
  <Player>
    <Rank>226</Rank>
    <Name>Zoro</Name>
    <XpEarned>33880</XpEarned>
  </Player>
  <Player>
    <Rank>227</Rank>
    <Name>Malekosala</Name>
    <XpEarned>31310</XpEarned>
  </Player>
  <Player>
    <Rank>228</Rank>
    <Name>Magoloko</Name>
    <XpEarned>26460</XpEarned>
  </Player>
  <Player>
    <Rank>229</Rank>
    <Name>Alfisyehh</Name>
    <XpEarned>4750</XpEarned>
  </Player>
  <Player>
    <Rank>230</Rank>
    <Name>Apollo</Name>
    <XpEarned>3640</XpEarned>
  </Player>
  <Player>
    <Rank>231</Rank>
    <Name>Maceio</Name>
    <XpEarned>2750</XpEarned>
  </Player>
  <Player>
    <Rank>232</Rank>
    <Name>Jensen</Name>
    <XpEarned>1386</XpEarned>
  </Player>
  <Player>
    <Rank>233</Rank>
    <Name>Astaroth </Name>
    <XpEarned>161</XpEarned>
  </Player>
  <Player>
    <Rank>234</Rank>
    <Name>Khorhigee</Name>
    <XpEarned>0</XpEarned>
  </Player>
  <Player>
    <Rank>235</Rank>
    <Name>Ramz</Name>
    <XpEarned>0</XpEarned>
  </Player>
  <Player>
    <Rank>236</Rank>
    <Name>Rider</Name>
    <XpEarned>0</XpEarned>
  </Player>
  <Player>
    <Rank>237</Rank>
    <Name>Kaparzo</Name>
    <XpEarned>0</XpEarned>
  </Player>
  <Player>
    <Rank>238</Rank>
    <Name>Xenaa</Name>
    <XpEarned>0</XpEarned>
  </Player>
  <Player>
    <Rank>239</Rank>
    <Name>Raulzito</Name>
    <XpEarned>0</XpEarned>
  </Player>
  <Player>
    <Rank>240</Rank>
    <Name>Jembei</Name>
    <XpEarned>0</XpEarned>
  </Player>
  <Player>
    <Rank>241</Rank>
    <Name>Yesim</Name>
    <XpEarned>0</XpEarned>
  </Player>
  <Player>
    <Rank>242</Rank>
    <Name>Kannizinha</Name>
    <XpEarned>-1648817</XpEarned>
  </Player>
  <Player>
    <Rank>243</Rank>
    <Name>Pierre</Name>
    <XpEarned>-6591147</XpEarned>
  </Player>
  <Player>
    <Rank>244</Rank>
    <Name>Brisadeiro</Name>
    <XpEarned>-6858420</XpEarned>
  </Player>
  <Player>
    <Rank>245</Rank>
    <Name>Urekmazino</Name>
    <XpEarned>-15276216</XpEarned>
  </Player>
  <Player>
    <Rank>246</Rank>
    <Name>Ikytbking</Name>
    <XpEarned>-21779693</XpEarned>
  </Player>
  <Player>
    <Rank>247</Rank>
    <Name>Khun</Name>
    <XpEarned>-22480982</XpEarned>
  </Player>
  <Player>
    <Rank>248</Rank>
    <Name>Brisadeira</Name>
    <XpEarned>-30620229</XpEarned>
  </Player>
  <Player>
    <Rank>249</Rank>
    <Name>Vizkal</Name>
    <XpEarned>-33888408</XpEarned>
  </Player>
  <Player>
    <Rank>250</Rank>
    <Name>Vinion</Name>
    <XpEarned>-50708804</XpEarned>
  </Player>
</DailyXpHighscores>
