<?xml version="1.0" encoding="UTF-8"?>
<DailyXpHighscores>
  <GeneratedAt>1751842806660</GeneratedAt>
  <Player>
    <Rank>1</Rank>
    <Name>Dandelions</Name>
    <XpEarned>104241399</XpEarned>
  </Player>
  <Player>
    <Rank>2</Rank>
    <Name>Kannisword</Name>
    <XpEarned>89296620</XpEarned>
  </Player>
  <Player>
    <Rank>3</Rank>
    <Name>Vulcano</Name>
    <XpEarned>84877310</XpEarned>
  </Player>
  <Player>
    <Rank>4</Rank>
    <Name>Willinha</Name>
    <XpEarned>78992660</XpEarned>
  </Player>
  <Player>
    <Rank>5</Rank>
    <Name>Cupy</Name>
    <XpEarned>76012852</XpEarned>
  </Player>
  <Player>
    <Rank>6</Rank>
    <Name>Pablo</Name>
    <XpEarned>70111160</XpEarned>
  </Player>
  <Player>
    <Rank>7</Rank>
    <Name>Papito</Name>
    <XpEarned>64647450</XpEarned>
  </Player>
  <Player>
    <Rank>8</Rank>
    <Name>Rog</Name>
    <XpEarned>64579060</XpEarned>
  </Player>
  <Player>
    <Rank>9</Rank>
    <Name>Hiroshi</Name>
    <XpEarned>59399550</XpEarned>
  </Player>
  <Player>
    <Rank>10</Rank>
    <Name>Exist</Name>
    <XpEarned>58630249</XpEarned>
  </Player>
  <Player>
    <Rank>11</Rank>
    <Name>Jeeje</Name>
    <XpEarned>57862140</XpEarned>
  </Player>
  <Player>
    <Rank>12</Rank>
    <Name>Warr</Name>
    <XpEarned>56528360</XpEarned>
  </Player>
  <Player>
    <Rank>13</Rank>
    <Name>Kakashi</Name>
    <XpEarned>56368601</XpEarned>
  </Player>
  <Player>
    <Rank>14</Rank>
    <Name>Rigger</Name>
    <XpEarned>56220440</XpEarned>
  </Player>
  <Player>
    <Rank>15</Rank>
    <Name>Castiel</Name>
    <XpEarned>51966445</XpEarned>
  </Player>
  <Player>
    <Rank>16</Rank>
    <Name>Templarr</Name>
    <XpEarned>48213866</XpEarned>
  </Player>
  <Player>
    <Rank>17</Rank>
    <Name>Maxx</Name>
    <XpEarned>47973940</XpEarned>
  </Player>
  <Player>
    <Rank>18</Rank>
    <Name>Akirz</Name>
    <XpEarned>47145859</XpEarned>
  </Player>
  <Player>
    <Rank>19</Rank>
    <Name>Kannibalz</Name>
    <XpEarned>45563140</XpEarned>
  </Player>
  <Player>
    <Rank>20</Rank>
    <Name>Tec</Name>
    <XpEarned>43679447</XpEarned>
  </Player>
  <Player>
    <Rank>21</Rank>
    <Name>Justen</Name>
    <XpEarned>43308513</XpEarned>
  </Player>
  <Player>
    <Rank>22</Rank>
    <Name>Alzeta</Name>
    <XpEarned>42025340</XpEarned>
  </Player>
  <Player>
    <Rank>23</Rank>
    <Name>Niggawiz</Name>
    <XpEarned>41571600</XpEarned>
  </Player>
  <Player>
    <Rank>24</Rank>
    <Name>Snob</Name>
    <XpEarned>40190506</XpEarned>
  </Player>
  <Player>
    <Rank>25</Rank>
    <Name>Panda</Name>
    <XpEarned>36634271</XpEarned>
  </Player>
  <Player>
    <Rank>26</Rank>
    <Name>Templar</Name>
    <XpEarned>35789835</XpEarned>
  </Player>
  <Player>
    <Rank>27</Rank>
    <Name>Pandatank</Name>
    <XpEarned>31956974</XpEarned>
  </Player>
  <Player>
    <Rank>28</Rank>
    <Name>Heineken</Name>
    <XpEarned>25703440</XpEarned>
  </Player>
  <Player>
    <Rank>29</Rank>
    <Name>Ashura</Name>
    <XpEarned>24851416</XpEarned>
  </Player>
  <Player>
    <Rank>30</Rank>
    <Name>Dblack</Name>
    <XpEarned>24365064</XpEarned>
  </Player>
  <Player>
    <Rank>31</Rank>
    <Name>Powerofgod</Name>
    <XpEarned>22960607</XpEarned>
  </Player>
  <Player>
    <Rank>32</Rank>
    <Name>Khorhigee</Name>
    <XpEarned>22751886</XpEarned>
  </Player>
  <Player>
    <Rank>33</Rank>
    <Name>Bruxo</Name>
    <XpEarned>21841664</XpEarned>
  </Player>
  <Player>
    <Rank>34</Rank>
    <Name>Dewezz</Name>
    <XpEarned>21610948</XpEarned>
  </Player>
  <Player>
    <Rank>35</Rank>
    <Name>Hakina</Name>
    <XpEarned>19096408</XpEarned>
  </Player>
  <Player>
    <Rank>36</Rank>
    <Name>Goldtanker</Name>
    <XpEarned>17936002</XpEarned>
  </Player>
  <Player>
    <Rank>37</Rank>
    <Name>Shadowww</Name>
    <XpEarned>17764335</XpEarned>
  </Player>
  <Player>
    <Rank>38</Rank>
    <Name>Wk</Name>
    <XpEarned>16463389</XpEarned>
  </Player>
  <Player>
    <Rank>39</Rank>
    <Name>Terrifier</Name>
    <XpEarned>16427152</XpEarned>
  </Player>
  <Player>
    <Rank>40</Rank>
    <Name>Salamaleko</Name>
    <XpEarned>15757653</XpEarned>
  </Player>
  <Player>
    <Rank>41</Rank>
    <Name>Artemis</Name>
    <XpEarned>15405110</XpEarned>
  </Player>
  <Player>
    <Rank>42</Rank>
    <Name>Datubiadap</Name>
    <XpEarned>14455674</XpEarned>
  </Player>
  <Player>
    <Rank>43</Rank>
    <Name>Joker</Name>
    <XpEarned>13279514</XpEarned>
  </Player>
  <Player>
    <Rank>44</Rank>
    <Name>Dewez</Name>
    <XpEarned>12489954</XpEarned>
  </Player>
  <Player>
    <Rank>45</Rank>
    <Name>Pageone</Name>
    <XpEarned>12403819</XpEarned>
  </Player>
  <Player>
    <Rank>46</Rank>
    <Name>Hellokitty</Name>
    <XpEarned>12327256</XpEarned>
  </Player>
  <Player>
    <Rank>47</Rank>
    <Name>Durin</Name>
    <XpEarned>12076239</XpEarned>
  </Player>
  <Player>
    <Rank>48</Rank>
    <Name>Talrok</Name>
    <XpEarned>11661650</XpEarned>
  </Player>
  <Player>
    <Rank>49</Rank>
    <Name>Madera</Name>
    <XpEarned>10514614</XpEarned>
  </Player>
  <Player>
    <Rank>50</Rank>
    <Name>Killer</Name>
    <XpEarned>10233300</XpEarned>
  </Player>
  <Player>
    <Rank>51</Rank>
    <Name>Ganny</Name>
    <XpEarned>9586070</XpEarned>
  </Player>
  <Player>
    <Rank>52</Rank>
    <Name>Kanki</Name>
    <XpEarned>8319181</XpEarned>
  </Player>
  <Player>
    <Rank>53</Rank>
    <Name>Supy</Name>
    <XpEarned>7916124</XpEarned>
  </Player>
  <Player>
    <Rank>54</Rank>
    <Name>Victorbr</Name>
    <XpEarned>7908780</XpEarned>
  </Player>
  <Player>
    <Rank>55</Rank>
    <Name>Borutos</Name>
    <XpEarned>7778729</XpEarned>
  </Player>
  <Player>
    <Rank>56</Rank>
    <Name>Justin</Name>
    <XpEarned>7571179</XpEarned>
  </Player>
  <Player>
    <Rank>57</Rank>
    <Name>Liontin</Name>
    <XpEarned>7330418</XpEarned>
  </Player>
  <Player>
    <Rank>58</Rank>
    <Name>Killerwiz</Name>
    <XpEarned>6549672</XpEarned>
  </Player>
  <Player>
    <Rank>59</Rank>
    <Name>Boruto</Name>
    <XpEarned>6461116</XpEarned>
  </Player>
  <Player>
    <Rank>60</Rank>
    <Name>Taz</Name>
    <XpEarned>5980352</XpEarned>
  </Player>
  <Player>
    <Rank>61</Rank>
    <Name>Guard</Name>
    <XpEarned>5600910</XpEarned>
  </Player>
  <Player>
    <Rank>62</Rank>
    <Name>Dyvnee</Name>
    <XpEarned>5079420</XpEarned>
  </Player>
  <Player>
    <Rank>63</Rank>
    <Name>Rei</Name>
    <XpEarned>4755548</XpEarned>
  </Player>
  <Player>
    <Rank>64</Rank>
    <Name>Shaday</Name>
    <XpEarned>4636524</XpEarned>
  </Player>
  <Player>
    <Rank>65</Rank>
    <Name>Khun</Name>
    <XpEarned>4383258</XpEarned>
  </Player>
  <Player>
    <Rank>66</Rank>
    <Name>Brisadeiro</Name>
    <XpEarned>4230450</XpEarned>
  </Player>
  <Player>
    <Rank>67</Rank>
    <Name>Over</Name>
    <XpEarned>4096110</XpEarned>
  </Player>
  <Player>
    <Rank>68</Rank>
    <Name>Brisadeira</Name>
    <XpEarned>3766657</XpEarned>
  </Player>
  <Player>
    <Rank>69</Rank>
    <Name>Gabriell</Name>
    <XpEarned>3598387</XpEarned>
  </Player>
  <Player>
    <Rank>70</Rank>
    <Name>Melkor</Name>
    <XpEarned>3589593</XpEarned>
  </Player>
  <Player>
    <Rank>71</Rank>
    <Name>Kannizinha</Name>
    <XpEarned>3584000</XpEarned>
  </Player>
  <Player>
    <Rank>72</Rank>
    <Name>Sxgabrielx</Name>
    <XpEarned>3486456</XpEarned>
  </Player>
  <Player>
    <Rank>73</Rank>
    <Name>Lendario</Name>
    <XpEarned>3440225</XpEarned>
  </Player>
  <Player>
    <Rank>74</Rank>
    <Name>Lordblack</Name>
    <XpEarned>3384645</XpEarned>
  </Player>
  <Player>
    <Rank>75</Rank>
    <Name>Hellwilzz</Name>
    <XpEarned>3339606</XpEarned>
  </Player>
  <Player>
    <Rank>76</Rank>
    <Name>Madara</Name>
    <XpEarned>3299242</XpEarned>
  </Player>
  <Player>
    <Rank>77</Rank>
    <Name>Aulia</Name>
    <XpEarned>3127187</XpEarned>
  </Player>
  <Player>
    <Rank>78</Rank>
    <Name>Vamplod</Name>
    <XpEarned>2997428</XpEarned>
  </Player>
  <Player>
    <Rank>79</Rank>
    <Name>Belzebugod</Name>
    <XpEarned>2948400</XpEarned>
  </Player>
  <Player>
    <Rank>80</Rank>
    <Name>Urekmazino</Name>
    <XpEarned>2924015</XpEarned>
  </Player>
  <Player>
    <Rank>81</Rank>
    <Name>Scott</Name>
    <XpEarned>2730162</XpEarned>
  </Player>
  <Player>
    <Rank>82</Rank>
    <Name>Xlucasx</Name>
    <XpEarned>2697003</XpEarned>
  </Player>
  <Player>
    <Rank>83</Rank>
    <Name>Reheli</Name>
    <XpEarned>2504250</XpEarned>
  </Player>
  <Player>
    <Rank>84</Rank>
    <Name>Qahderijan</Name>
    <XpEarned>2403879</XpEarned>
  </Player>
  <Player>
    <Rank>85</Rank>
    <Name>Dark</Name>
    <XpEarned>2052600</XpEarned>
  </Player>
  <Player>
    <Rank>86</Rank>
    <Name>Eunha</Name>
    <XpEarned>2009304</XpEarned>
  </Player>
  <Player>
    <Rank>87</Rank>
    <Name>Kratos</Name>
    <XpEarned>1964400</XpEarned>
  </Player>
  <Player>
    <Rank>88</Rank>
    <Name>Matadordpk</Name>
    <XpEarned>1949588</XpEarned>
  </Player>
  <Player>
    <Rank>89</Rank>
    <Name>Vulion </Name>
    <XpEarned>1900291</XpEarned>
  </Player>
  <Player>
    <Rank>90</Rank>
    <Name>Sheman</Name>
    <XpEarned>1839600</XpEarned>
  </Player>
  <Player>
    <Rank>91</Rank>
    <Name>Astreus</Name>
    <XpEarned>1745945</XpEarned>
  </Player>
  <Player>
    <Rank>92</Rank>
    <Name>Renansz</Name>
    <XpEarned>1682890</XpEarned>
  </Player>
  <Player>
    <Rank>93</Rank>
    <Name>Sexi</Name>
    <XpEarned>1643796</XpEarned>
  </Player>
  <Player>
    <Rank>94</Rank>
    <Name>Tiringa </Name>
    <XpEarned>1457498</XpEarned>
  </Player>
  <Player>
    <Rank>95</Rank>
    <Name>Danzou</Name>
    <XpEarned>1439639</XpEarned>
  </Player>
  <Player>
    <Rank>96</Rank>
    <Name>Galadriel</Name>
    <XpEarned>1425000</XpEarned>
  </Player>
  <Player>
    <Rank>97</Rank>
    <Name>Liaauliaa</Name>
    <XpEarned>1425000</XpEarned>
  </Player>
  <Player>
    <Rank>98</Rank>
    <Name>Bonilha</Name>
    <XpEarned>1425000</XpEarned>
  </Player>
  <Player>
    <Rank>99</Rank>
    <Name>Nauk</Name>
    <XpEarned>1404585</XpEarned>
  </Player>
  <Player>
    <Rank>100</Rank>
    <Name>Piras</Name>
    <XpEarned>1336300</XpEarned>
  </Player>
  <Player>
    <Rank>101</Rank>
    <Name>Poppay</Name>
    <XpEarned>1289750</XpEarned>
  </Player>
  <Player>
    <Rank>102</Rank>
    <Name>Nena</Name>
    <XpEarned>1274490</XpEarned>
  </Player>
  <Player>
    <Rank>103</Rank>
    <Name>Crydevilz</Name>
    <XpEarned>1193879</XpEarned>
  </Player>
  <Player>
    <Rank>104</Rank>
    <Name>Gacorrr</Name>
    <XpEarned>1101870</XpEarned>
  </Player>
  <Player>
    <Rank>105</Rank>
    <Name>Sungjinwoo</Name>
    <XpEarned>997360</XpEarned>
  </Player>
  <Player>
    <Rank>106</Rank>
    <Name>Bamor</Name>
    <XpEarned>954240</XpEarned>
  </Player>
  <Player>
    <Rank>107</Rank>
    <Name>Alegria</Name>
    <XpEarned>926558</XpEarned>
  </Player>
  <Player>
    <Rank>108</Rank>
    <Name>Leader</Name>
    <XpEarned>922600</XpEarned>
  </Player>
  <Player>
    <Rank>109</Rank>
    <Name>Maddevilz</Name>
    <XpEarned>917644</XpEarned>
  </Player>
  <Player>
    <Rank>110</Rank>
    <Name>Magrela</Name>
    <XpEarned>896780</XpEarned>
  </Player>
  <Player>
    <Rank>111</Rank>
    <Name>Dinastia</Name>
    <XpEarned>880425</XpEarned>
  </Player>
  <Player>
    <Rank>112</Rank>
    <Name>Soft</Name>
    <XpEarned>745733</XpEarned>
  </Player>
  <Player>
    <Rank>113</Rank>
    <Name>Dressrossa</Name>
    <XpEarned>741195</XpEarned>
  </Player>
  <Player>
    <Rank>114</Rank>
    <Name>Afk</Name>
    <XpEarned>696092</XpEarned>
  </Player>
  <Player>
    <Rank>115</Rank>
    <Name>Bii</Name>
    <XpEarned>662440</XpEarned>
  </Player>
  <Player>
    <Rank>116</Rank>
    <Name>Ryten</Name>
    <XpEarned>630000</XpEarned>
  </Player>
  <Player>
    <Rank>117</Rank>
    <Name>Destino</Name>
    <XpEarned>586205</XpEarned>
  </Player>
  <Player>
    <Rank>118</Rank>
    <Name>Axionshure</Name>
    <XpEarned>564200</XpEarned>
  </Player>
  <Player>
    <Rank>119</Rank>
    <Name>Lessaka</Name>
    <XpEarned>501932</XpEarned>
  </Player>
  <Player>
    <Rank>120</Rank>
    <Name>Royalshdow</Name>
    <XpEarned>465920</XpEarned>
  </Player>
  <Player>
    <Rank>121</Rank>
    <Name>Doze</Name>
    <XpEarned>414980</XpEarned>
  </Player>
  <Player>
    <Rank>122</Rank>
    <Name>Riquekmila</Name>
    <XpEarned>408539</XpEarned>
  </Player>
  <Player>
    <Rank>123</Rank>
    <Name>Borala</Name>
    <XpEarned>407976</XpEarned>
  </Player>
  <Player>
    <Rank>124</Rank>
    <Name>Lukzinsk</Name>
    <XpEarned>351680</XpEarned>
  </Player>
  <Player>
    <Rank>125</Rank>
    <Name>Dez</Name>
    <XpEarned>332325</XpEarned>
  </Player>
  <Player>
    <Rank>126</Rank>
    <Name>Sete</Name>
    <XpEarned>264600</XpEarned>
  </Player>
  <Player>
    <Rank>127</Rank>
    <Name>Nove</Name>
    <XpEarned>231525</XpEarned>
  </Player>
  <Player>
    <Rank>128</Rank>
    <Name>Tres</Name>
    <XpEarned>224217</XpEarned>
  </Player>
  <Player>
    <Rank>129</Rank>
    <Name>Onze</Name>
    <XpEarned>151200</XpEarned>
  </Player>
  <Player>
    <Rank>130</Rank>
    <Name>Oito</Name>
    <XpEarned>149625</XpEarned>
  </Player>
  <Player>
    <Rank>131</Rank>
    <Name>Hammers</Name>
    <XpEarned>91712</XpEarned>
  </Player>
  <Player>
    <Rank>132</Rank>
    <Name>Red</Name>
    <XpEarned>68355</XpEarned>
  </Player>
  <Player>
    <Rank>133</Rank>
    <Name>Ghostface</Name>
    <XpEarned>44100</XpEarned>
  </Player>
  <Player>
    <Rank>134</Rank>
    <Name>Troyn</Name>
    <XpEarned>2520</XpEarned>
  </Player>
  <Player>
    <Rank>135</Rank>
    <Name>Uili</Name>
    <XpEarned>1645</XpEarned>
  </Player>
  <Player>
    <Rank>136</Rank>
    <Name>Bira</Name>
    <XpEarned>0</XpEarned>
  </Player>
  <Player>
    <Rank>137</Rank>
    <Name>Alyo</Name>
    <XpEarned>0</XpEarned>
  </Player>
  <Player>
    <Rank>138</Rank>
    <Name>Hamura</Name>
    <XpEarned>0</XpEarned>
  </Player>
  <Player>
    <Rank>139</Rank>
    <Name>Zhouzinn</Name>
    <XpEarned>0</XpEarned>
  </Player>
</DailyXpHighscores>
