<?xml version="1.0" encoding="UTF-8"?>
<DailyXpHighscores>
  <GeneratedAt>1750098698228</GeneratedAt>
  <Player>
    <Rank>1</Rank>
    <Name>Pancernik</Name>
    <XpEarned>631421603</XpEarned>
  </Player>
  <Player>
    <Rank>2</Rank>
    <Name>Mii</Name>
    <XpEarned>522342185</XpEarned>
  </Player>
  <Player>
    <Rank>3</Rank>
    <Name>Hiroshi</Name>
    <XpEarned>516527534</XpEarned>
  </Player>
  <Player>
    <Rank>4</Rank>
    <Name>Papito</Name>
    <XpEarned>488374213</XpEarned>
  </Player>
  <Player>
    <Rank>5</Rank>
    <Name>Kannisword</Name>
    <XpEarned>445092734</XpEarned>
  </Player>
  <Player>
    <Rank>6</Rank>
    <Name>Wk</Name>
    <XpEarned>420099043</XpEarned>
  </Player>
  <Player>
    <Rank>7</Rank>
    <Name>Cupy</Name>
    <XpEarned>378094035</XpEarned>
  </Player>
  <Player>
    <Rank>8</Rank>
    <Name>Exist</Name>
    <XpEarned>369067669</XpEarned>
  </Player>
  <Player>
    <Rank>9</Rank>
    <Name>Digdin</Name>
    <XpEarned>364601798</XpEarned>
  </Player>
  <Player>
    <Rank>10</Rank>
    <Name>Hawkeyez</Name>
    <XpEarned>360175283</XpEarned>
  </Player>
  <Player>
    <Rank>11</Rank>
    <Name>Datubiadap</Name>
    <XpEarned>358425900</XpEarned>
  </Player>
  <Player>
    <Rank>12</Rank>
    <Name>Maxx</Name>
    <XpEarned>336352603</XpEarned>
  </Player>
  <Player>
    <Rank>13</Rank>
    <Name>Gaspar</Name>
    <XpEarned>328697104</XpEarned>
  </Player>
  <Player>
    <Rank>14</Rank>
    <Name>Kannibalz</Name>
    <XpEarned>322475580</XpEarned>
  </Player>
  <Player>
    <Rank>15</Rank>
    <Name>Pintoral</Name>
    <XpEarned>307181419</XpEarned>
  </Player>
  <Player>
    <Rank>16</Rank>
    <Name>Kingdeus</Name>
    <XpEarned>289789272</XpEarned>
  </Player>
  <Player>
    <Rank>17</Rank>
    <Name>Kakashi</Name>
    <XpEarned>285269938</XpEarned>
  </Player>
  <Player>
    <Rank>18</Rank>
    <Name>Serizawa</Name>
    <XpEarned>280930598</XpEarned>
  </Player>
  <Player>
    <Rank>19</Rank>
    <Name>Buca</Name>
    <XpEarned>277770780</XpEarned>
  </Player>
  <Player>
    <Rank>20</Rank>
    <Name>Hamura</Name>
    <XpEarned>264622680</XpEarned>
  </Player>
  <Player>
    <Rank>21</Rank>
    <Name>Over</Name>
    <XpEarned>245807982</XpEarned>
  </Player>
  <Player>
    <Rank>22</Rank>
    <Name>Saskeh</Name>
    <XpEarned>239165513</XpEarned>
  </Player>
  <Player>
    <Rank>23</Rank>
    <Name>Joker</Name>
    <XpEarned>231251694</XpEarned>
  </Player>
  <Player>
    <Rank>24</Rank>
    <Name>Vamplod</Name>
    <XpEarned>230273097</XpEarned>
  </Player>
  <Player>
    <Rank>25</Rank>
    <Name>Zed</Name>
    <XpEarned>229215276</XpEarned>
  </Player>
  <Player>
    <Rank>26</Rank>
    <Name>Warr</Name>
    <XpEarned>223867870</XpEarned>
  </Player>
  <Player>
    <Rank>27</Rank>
    <Name>Mitt</Name>
    <XpEarned>217885470</XpEarned>
  </Player>
  <Player>
    <Rank>28</Rank>
    <Name>Alzeta</Name>
    <XpEarned>210770389</XpEarned>
  </Player>
  <Player>
    <Rank>29</Rank>
    <Name>Yoshikazu</Name>
    <XpEarned>206747547</XpEarned>
  </Player>
  <Player>
    <Rank>30</Rank>
    <Name>Jeeje</Name>
    <XpEarned>196492647</XpEarned>
  </Player>
  <Player>
    <Rank>31</Rank>
    <Name>Kingkiller</Name>
    <XpEarned>195088397</XpEarned>
  </Player>
  <Player>
    <Rank>32</Rank>
    <Name>Kibo</Name>
    <XpEarned>193910943</XpEarned>
  </Player>
  <Player>
    <Rank>33</Rank>
    <Name>Niggawiz</Name>
    <XpEarned>188953933</XpEarned>
  </Player>
  <Player>
    <Rank>34</Rank>
    <Name>Gasparwiz</Name>
    <XpEarned>187854999</XpEarned>
  </Player>
  <Player>
    <Rank>35</Rank>
    <Name>Castiel</Name>
    <XpEarned>162879537</XpEarned>
  </Player>
  <Player>
    <Rank>36</Rank>
    <Name>Victorbr</Name>
    <XpEarned>162876951</XpEarned>
  </Player>
  <Player>
    <Rank>37</Rank>
    <Name>Dyvnee</Name>
    <XpEarned>147309873</XpEarned>
  </Player>
  <Player>
    <Rank>38</Rank>
    <Name>Willinha </Name>
    <XpEarned>131471354</XpEarned>
  </Player>
  <Player>
    <Rank>39</Rank>
    <Name>Rog</Name>
    <XpEarned>127238021</XpEarned>
  </Player>
  <Player>
    <Rank>40</Rank>
    <Name>Bruxo</Name>
    <XpEarned>126103221</XpEarned>
  </Player>
  <Player>
    <Rank>41</Rank>
    <Name>Dom</Name>
    <XpEarned>114938765</XpEarned>
  </Player>
  <Player>
    <Rank>42</Rank>
    <Name>Pageone</Name>
    <XpEarned>108080067</XpEarned>
  </Player>
  <Player>
    <Rank>43</Rank>
    <Name>Victorwiz</Name>
    <XpEarned>104918002</XpEarned>
  </Player>
  <Player>
    <Rank>44</Rank>
    <Name>Guinny</Name>
    <XpEarned>97786136</XpEarned>
  </Player>
  <Player>
    <Rank>45</Rank>
    <Name>Rigger</Name>
    <XpEarned>89574912</XpEarned>
  </Player>
  <Player>
    <Rank>46</Rank>
    <Name>Trovao</Name>
    <XpEarned>86846937</XpEarned>
  </Player>
  <Player>
    <Rank>47</Rank>
    <Name>Templarr</Name>
    <XpEarned>86293364</XpEarned>
  </Player>
  <Player>
    <Rank>48</Rank>
    <Name>Dewezz</Name>
    <XpEarned>86018234</XpEarned>
  </Player>
  <Player>
    <Rank>49</Rank>
    <Name>Borutos</Name>
    <XpEarned>84616741</XpEarned>
  </Player>
  <Player>
    <Rank>50</Rank>
    <Name>Redeon</Name>
    <XpEarned>81979062</XpEarned>
  </Player>
  <Player>
    <Rank>51</Rank>
    <Name>Salamaleko</Name>
    <XpEarned>74690295</XpEarned>
  </Player>
  <Player>
    <Rank>52</Rank>
    <Name>Pablo</Name>
    <XpEarned>73414870</XpEarned>
  </Player>
  <Player>
    <Rank>53</Rank>
    <Name>Scott</Name>
    <XpEarned>71526221</XpEarned>
  </Player>
  <Player>
    <Rank>54</Rank>
    <Name>Killerdark</Name>
    <XpEarned>71267274</XpEarned>
  </Player>
  <Player>
    <Rank>55</Rank>
    <Name>Talrok</Name>
    <XpEarned>70821606</XpEarned>
  </Player>
  <Player>
    <Rank>56</Rank>
    <Name>Terrifier</Name>
    <XpEarned>67933218</XpEarned>
  </Player>
  <Player>
    <Rank>57</Rank>
    <Name>Shadowww</Name>
    <XpEarned>63724355</XpEarned>
  </Player>
  <Player>
    <Rank>58</Rank>
    <Name>Durin</Name>
    <XpEarned>62252067</XpEarned>
  </Player>
  <Player>
    <Rank>59</Rank>
    <Name>Hellokitty</Name>
    <XpEarned>61094226</XpEarned>
  </Player>
  <Player>
    <Rank>60</Rank>
    <Name>Srlira</Name>
    <XpEarned>57480600</XpEarned>
  </Player>
  <Player>
    <Rank>61</Rank>
    <Name>Loki</Name>
    <XpEarned>57036369</XpEarned>
  </Player>
  <Player>
    <Rank>62</Rank>
    <Name>Genji</Name>
    <XpEarned>54499135</XpEarned>
  </Player>
  <Player>
    <Rank>63</Rank>
    <Name>Goldtanker</Name>
    <XpEarned>51403192</XpEarned>
  </Player>
  <Player>
    <Rank>64</Rank>
    <Name>Dblack</Name>
    <XpEarned>50685331</XpEarned>
  </Player>
  <Player>
    <Rank>65</Rank>
    <Name>Dewez</Name>
    <XpEarned>50005761</XpEarned>
  </Player>
  <Player>
    <Rank>66</Rank>
    <Name>Soft</Name>
    <XpEarned>49563875</XpEarned>
  </Player>
  <Player>
    <Rank>67</Rank>
    <Name>Kingsblack</Name>
    <XpEarned>49259191</XpEarned>
  </Player>
  <Player>
    <Rank>68</Rank>
    <Name>Astreus</Name>
    <XpEarned>47191388</XpEarned>
  </Player>
  <Player>
    <Rank>69</Rank>
    <Name>Killer</Name>
    <XpEarned>46696112</XpEarned>
  </Player>
  <Player>
    <Rank>70</Rank>
    <Name>Madara</Name>
    <XpEarned>45107712</XpEarned>
  </Player>
  <Player>
    <Rank>71</Rank>
    <Name>Panda</Name>
    <XpEarned>43681559</XpEarned>
  </Player>
  <Player>
    <Rank>72</Rank>
    <Name>Gandalf</Name>
    <XpEarned>42370006</XpEarned>
  </Player>
  <Player>
    <Rank>73</Rank>
    <Name>Rokz</Name>
    <XpEarned>42329746</XpEarned>
  </Player>
  <Player>
    <Rank>74</Rank>
    <Name>Blindadu</Name>
    <XpEarned>42294186</XpEarned>
  </Player>
  <Player>
    <Rank>75</Rank>
    <Name>Panqueca </Name>
    <XpEarned>39633822</XpEarned>
  </Player>
  <Player>
    <Rank>76</Rank>
    <Name>Boruto</Name>
    <XpEarned>36070415</XpEarned>
  </Player>
  <Player>
    <Rank>77</Rank>
    <Name>Piraswiz</Name>
    <XpEarned>32940768</XpEarned>
  </Player>
  <Player>
    <Rank>78</Rank>
    <Name>Zeboostin</Name>
    <XpEarned>32478278</XpEarned>
  </Player>
  <Player>
    <Rank>79</Rank>
    <Name>Killerwiz</Name>
    <XpEarned>32119308</XpEarned>
  </Player>
  <Player>
    <Rank>80</Rank>
    <Name>Tsuyoshi</Name>
    <XpEarned>30612953</XpEarned>
  </Player>
  <Player>
    <Rank>81</Rank>
    <Name>Poppay</Name>
    <XpEarned>29495819</XpEarned>
  </Player>
  <Player>
    <Rank>82</Rank>
    <Name>Bebelaq</Name>
    <XpEarned>27926494</XpEarned>
  </Player>
  <Player>
    <Rank>83</Rank>
    <Name>Hypertank</Name>
    <XpEarned>27807470</XpEarned>
  </Player>
  <Player>
    <Rank>84</Rank>
    <Name>Mit</Name>
    <XpEarned>26779262</XpEarned>
  </Player>
  <Player>
    <Rank>85</Rank>
    <Name>Knight</Name>
    <XpEarned>26583977</XpEarned>
  </Player>
  <Player>
    <Rank>86</Rank>
    <Name>Mi</Name>
    <XpEarned>25912591</XpEarned>
  </Player>
  <Player>
    <Rank>87</Rank>
    <Name>Seis</Name>
    <XpEarned>24573845</XpEarned>
  </Player>
  <Player>
    <Rank>88</Rank>
    <Name>Wizze</Name>
    <XpEarned>22037533</XpEarned>
  </Player>
  <Player>
    <Rank>89</Rank>
    <Name>Lordblack</Name>
    <XpEarned>21585474</XpEarned>
  </Player>
  <Player>
    <Rank>90</Rank>
    <Name>Destino</Name>
    <XpEarned>21576041</XpEarned>
  </Player>
  <Player>
    <Rank>91</Rank>
    <Name>Urekmazino</Name>
    <XpEarned>20487300</XpEarned>
  </Player>
  <Player>
    <Rank>92</Rank>
    <Name>Lendario</Name>
    <XpEarned>20274535</XpEarned>
  </Player>
  <Player>
    <Rank>93</Rank>
    <Name>Baam</Name>
    <XpEarned>20211939</XpEarned>
  </Player>
  <Player>
    <Rank>94</Rank>
    <Name>Cinco</Name>
    <XpEarned>19754516</XpEarned>
  </Player>
  <Player>
    <Rank>95</Rank>
    <Name>Enio</Name>
    <XpEarned>19745264</XpEarned>
  </Player>
  <Player>
    <Rank>96</Rank>
    <Name>Templar</Name>
    <XpEarned>18970216</XpEarned>
  </Player>
  <Player>
    <Rank>97</Rank>
    <Name>Reheli</Name>
    <XpEarned>18520403</XpEarned>
  </Player>
  <Player>
    <Rank>98</Rank>
    <Name>Sunrakul</Name>
    <XpEarned>18323532</XpEarned>
  </Player>
  <Player>
    <Rank>99</Rank>
    <Name>Blindada</Name>
    <XpEarned>16698371</XpEarned>
  </Player>
  <Player>
    <Rank>100</Rank>
    <Name>Quatro</Name>
    <XpEarned>16533355</XpEarned>
  </Player>
  <Player>
    <Rank>101</Rank>
    <Name>Snob</Name>
    <XpEarned>16517427</XpEarned>
  </Player>
  <Player>
    <Rank>102</Rank>
    <Name>Ganny</Name>
    <XpEarned>16516787</XpEarned>
  </Player>
  <Player>
    <Rank>103</Rank>
    <Name>Zhouzinn</Name>
    <XpEarned>16485552</XpEarned>
  </Player>
  <Player>
    <Rank>104</Rank>
    <Name>Sunrako</Name>
    <XpEarned>16060874</XpEarned>
  </Player>
  <Player>
    <Rank>105</Rank>
    <Name>Quebeck</Name>
    <XpEarned>15380693</XpEarned>
  </Player>
  <Player>
    <Rank>106</Rank>
    <Name>Sxgabrielx</Name>
    <XpEarned>15290633</XpEarned>
  </Player>
  <Player>
    <Rank>107</Rank>
    <Name>Nauk</Name>
    <XpEarned>14841332</XpEarned>
  </Player>
  <Player>
    <Rank>108</Rank>
    <Name>Hakina</Name>
    <XpEarned>14683550</XpEarned>
  </Player>
  <Player>
    <Rank>109</Rank>
    <Name>Khun</Name>
    <XpEarned>14353760</XpEarned>
  </Player>
  <Player>
    <Rank>110</Rank>
    <Name>Blindao</Name>
    <XpEarned>14230551</XpEarned>
  </Player>
  <Player>
    <Rank>111</Rank>
    <Name>Vegapunk</Name>
    <XpEarned>13780473</XpEarned>
  </Player>
  <Player>
    <Rank>112</Rank>
    <Name>Magezin</Name>
    <XpEarned>13404960</XpEarned>
  </Player>
  <Player>
    <Rank>113</Rank>
    <Name>Kelavan</Name>
    <XpEarned>13197749</XpEarned>
  </Player>
  <Player>
    <Rank>114</Rank>
    <Name>Dogs</Name>
    <XpEarned>12657005</XpEarned>
  </Player>
  <Player>
    <Rank>115</Rank>
    <Name>Ainz</Name>
    <XpEarned>12266766</XpEarned>
  </Player>
  <Player>
    <Rank>116</Rank>
    <Name>Redzin</Name>
    <XpEarned>11668860</XpEarned>
  </Player>
  <Player>
    <Rank>117</Rank>
    <Name>Movie</Name>
    <XpEarned>11538022</XpEarned>
  </Player>
  <Player>
    <Rank>118</Rank>
    <Name>Sakura</Name>
    <XpEarned>11530999</XpEarned>
  </Player>
  <Player>
    <Rank>119</Rank>
    <Name>Blindado</Name>
    <XpEarned>11492164</XpEarned>
  </Player>
  <Player>
    <Rank>120</Rank>
    <Name>Nena</Name>
    <XpEarned>10856113</XpEarned>
  </Player>
  <Player>
    <Rank>121</Rank>
    <Name>Eloa</Name>
    <XpEarned>10803601</XpEarned>
  </Player>
  <Player>
    <Rank>122</Rank>
    <Name>Srluis</Name>
    <XpEarned>10496244</XpEarned>
  </Player>
  <Player>
    <Rank>123</Rank>
    <Name>Xxfuxx</Name>
    <XpEarned>9625526</XpEarned>
  </Player>
  <Player>
    <Rank>124</Rank>
    <Name>Zahard</Name>
    <XpEarned>9544977</XpEarned>
  </Player>
  <Player>
    <Rank>125</Rank>
    <Name>Goldwizz</Name>
    <XpEarned>8830800</XpEarned>
  </Player>
  <Player>
    <Rank>126</Rank>
    <Name>Rei</Name>
    <XpEarned>8440546</XpEarned>
  </Player>
  <Player>
    <Rank>127</Rank>
    <Name>Gacorrr</Name>
    <XpEarned>8375276</XpEarned>
  </Player>
  <Player>
    <Rank>128</Rank>
    <Name>Nenawiz</Name>
    <XpEarned>8231676</XpEarned>
  </Player>
  <Player>
    <Rank>129</Rank>
    <Name>Exor</Name>
    <XpEarned>8029419</XpEarned>
  </Player>
  <Player>
    <Rank>130</Rank>
    <Name>Goldwiz</Name>
    <XpEarned>7831090</XpEarned>
  </Player>
  <Player>
    <Rank>131</Rank>
    <Name>Spellwiz</Name>
    <XpEarned>7523671</XpEarned>
  </Player>
  <Player>
    <Rank>132</Rank>
    <Name>Galadriel</Name>
    <XpEarned>7480889</XpEarned>
  </Player>
  <Player>
    <Rank>133</Rank>
    <Name>Heineken</Name>
    <XpEarned>7301784</XpEarned>
  </Player>
  <Player>
    <Rank>134</Rank>
    <Name>Dragonbr</Name>
    <XpEarned>6656496</XpEarned>
  </Player>
  <Player>
    <Rank>135</Rank>
    <Name>Sunraku</Name>
    <XpEarned>5970853</XpEarned>
  </Player>
  <Player>
    <Rank>136</Rank>
    <Name>Babydoll</Name>
    <XpEarned>5556912</XpEarned>
  </Player>
  <Player>
    <Rank>137</Rank>
    <Name>Shaog</Name>
    <XpEarned>5077810</XpEarned>
  </Player>
  <Player>
    <Rank>138</Rank>
    <Name>Sunraka</Name>
    <XpEarned>4825581</XpEarned>
  </Player>
  <Player>
    <Rank>139</Rank>
    <Name>Goldwizzz</Name>
    <XpEarned>4787641</XpEarned>
  </Player>
  <Player>
    <Rank>140</Rank>
    <Name>Dexterr</Name>
    <XpEarned>4381989</XpEarned>
  </Player>
  <Player>
    <Rank>141</Rank>
    <Name>Tec</Name>
    <XpEarned>3864567</XpEarned>
  </Player>
  <Player>
    <Rank>142</Rank>
    <Name>Lorded</Name>
    <XpEarned>3837008</XpEarned>
  </Player>
  <Player>
    <Rank>143</Rank>
    <Name>Ghost</Name>
    <XpEarned>3614761</XpEarned>
  </Player>
  <Player>
    <Rank>144</Rank>
    <Name>Tuyull</Name>
    <XpEarned>3541181</XpEarned>
  </Player>
  <Player>
    <Rank>145</Rank>
    <Name>Liontin</Name>
    <XpEarned>3236107</XpEarned>
  </Player>
  <Player>
    <Rank>146</Rank>
    <Name>Michael </Name>
    <XpEarned>3185537</XpEarned>
  </Player>
  <Player>
    <Rank>147</Rank>
    <Name>Izuko</Name>
    <XpEarned>2938104</XpEarned>
  </Player>
  <Player>
    <Rank>148</Rank>
    <Name>Magicol</Name>
    <XpEarned>2868536</XpEarned>
  </Player>
  <Player>
    <Rank>149</Rank>
    <Name>Rureda</Name>
    <XpEarned>2330826</XpEarned>
  </Player>
  <Player>
    <Rank>150</Rank>
    <Name>Qiu</Name>
    <XpEarned>2328750</XpEarned>
  </Player>
  <Player>
    <Rank>151</Rank>
    <Name>Raphaooo</Name>
    <XpEarned>2309698</XpEarned>
  </Player>
  <Player>
    <Rank>152</Rank>
    <Name>Liliks</Name>
    <XpEarned>2272447</XpEarned>
  </Player>
  <Player>
    <Rank>153</Rank>
    <Name>Papeka</Name>
    <XpEarned>2162203</XpEarned>
  </Player>
  <Player>
    <Rank>154</Rank>
    <Name>Finorium</Name>
    <XpEarned>1935645</XpEarned>
  </Player>
  <Player>
    <Rank>155</Rank>
    <Name>Dexterwiz</Name>
    <XpEarned>1611621</XpEarned>
  </Player>
  <Player>
    <Rank>156</Rank>
    <Name>Kila</Name>
    <XpEarned>1455492</XpEarned>
  </Player>
  <Player>
    <Rank>157</Rank>
    <Name>Noia</Name>
    <XpEarned>1436458</XpEarned>
  </Player>
  <Player>
    <Rank>158</Rank>
    <Name>Valkiria</Name>
    <XpEarned>1425000</XpEarned>
  </Player>
  <Player>
    <Rank>159</Rank>
    <Name>Magrinn</Name>
    <XpEarned>1425000</XpEarned>
  </Player>
  <Player>
    <Rank>160</Rank>
    <Name>Godmagro</Name>
    <XpEarned>1425000</XpEarned>
  </Player>
  <Player>
    <Rank>161</Rank>
    <Name>Magroso</Name>
    <XpEarned>1425000</XpEarned>
  </Player>
  <Player>
    <Rank>162</Rank>
    <Name>Newege</Name>
    <XpEarned>1244423</XpEarned>
  </Player>
  <Player>
    <Rank>163</Rank>
    <Name>Crydevilz</Name>
    <XpEarned>1191481</XpEarned>
  </Player>
  <Player>
    <Rank>164</Rank>
    <Name>Riquekmila</Name>
    <XpEarned>1158491</XpEarned>
  </Player>
  <Player>
    <Rank>165</Rank>
    <Name>Vandamez</Name>
    <XpEarned>1037610</XpEarned>
  </Player>
  <Player>
    <Rank>166</Rank>
    <Name>Abgkumis</Name>
    <XpEarned>950000</XpEarned>
  </Player>
  <Player>
    <Rank>167</Rank>
    <Name>Pandatank</Name>
    <XpEarned>928607</XpEarned>
  </Player>
  <Player>
    <Rank>168</Rank>
    <Name>Kannizinha</Name>
    <XpEarned>894408</XpEarned>
  </Player>
  <Player>
    <Rank>169</Rank>
    <Name>Xelno</Name>
    <XpEarned>861317</XpEarned>
  </Player>
  <Player>
    <Rank>170</Rank>
    <Name>Gabriell</Name>
    <XpEarned>846265</XpEarned>
  </Player>
  <Player>
    <Rank>171</Rank>
    <Name>Skyrim</Name>
    <XpEarned>845622</XpEarned>
  </Player>
  <Player>
    <Rank>172</Rank>
    <Name>Penniswise</Name>
    <XpEarned>785143</XpEarned>
  </Player>
  <Player>
    <Rank>173</Rank>
    <Name>Ravena</Name>
    <XpEarned>766397</XpEarned>
  </Player>
  <Player>
    <Rank>174</Rank>
    <Name>Kaparzo</Name>
    <XpEarned>740625</XpEarned>
  </Player>
  <Player>
    <Rank>175</Rank>
    <Name>Arlequina</Name>
    <XpEarned>710424</XpEarned>
  </Player>
  <Player>
    <Rank>176</Rank>
    <Name>Pablinhu</Name>
    <XpEarned>709644</XpEarned>
  </Player>
  <Player>
    <Rank>177</Rank>
    <Name>Mihawk</Name>
    <XpEarned>615809</XpEarned>
  </Player>
  <Player>
    <Rank>178</Rank>
    <Name>Kant</Name>
    <XpEarned>502224</XpEarned>
  </Player>
  <Player>
    <Rank>179</Rank>
    <Name>Sasori</Name>
    <XpEarned>500000</XpEarned>
  </Player>
  <Player>
    <Rank>180</Rank>
    <Name>Magrelo</Name>
    <XpEarned>500000</XpEarned>
  </Player>
  <Player>
    <Rank>181</Rank>
    <Name>Konan</Name>
    <XpEarned>500000</XpEarned>
  </Player>
  <Player>
    <Rank>182</Rank>
    <Name>Captainz</Name>
    <XpEarned>483433</XpEarned>
  </Player>
  <Player>
    <Rank>183</Rank>
    <Name>Gaspazinho</Name>
    <XpEarned>475000</XpEarned>
  </Player>
  <Player>
    <Rank>184</Rank>
    <Name>Zyn</Name>
    <XpEarned>463193</XpEarned>
  </Player>
  <Player>
    <Rank>185</Rank>
    <Name>Sunrakowiz</Name>
    <XpEarned>392996</XpEarned>
  </Player>
  <Player>
    <Rank>186</Rank>
    <Name>Doncorazon</Name>
    <XpEarned>382050</XpEarned>
  </Player>
  <Player>
    <Rank>187</Rank>
    <Name>Fzkeblorcr</Name>
    <XpEarned>317520</XpEarned>
  </Player>
  <Player>
    <Rank>188</Rank>
    <Name>Kanki</Name>
    <XpEarned>279762</XpEarned>
  </Player>
  <Player>
    <Rank>189</Rank>
    <Name>Pedemesa</Name>
    <XpEarned>275000</XpEarned>
  </Player>
  <Player>
    <Rank>190</Rank>
    <Name>Cedric</Name>
    <XpEarned>265598</XpEarned>
  </Player>
  <Player>
    <Rank>191</Rank>
    <Name>And</Name>
    <XpEarned>251225</XpEarned>
  </Player>
  <Player>
    <Rank>192</Rank>
    <Name>Tifudi</Name>
    <XpEarned>121680</XpEarned>
  </Player>
  <Player>
    <Rank>193</Rank>
    <Name>Dewes</Name>
    <XpEarned>117372</XpEarned>
  </Player>
  <Player>
    <Rank>194</Rank>
    <Name>Mrdoman</Name>
    <XpEarned>89943</XpEarned>
  </Player>
  <Player>
    <Rank>195</Rank>
    <Name>Holl</Name>
    <XpEarned>86636</XpEarned>
  </Player>
  <Player>
    <Rank>196</Rank>
    <Name>Bsm</Name>
    <XpEarned>77814</XpEarned>
  </Player>
  <Player>
    <Rank>197</Rank>
    <Name>Katalixo</Name>
    <XpEarned>72900</XpEarned>
  </Player>
  <Player>
    <Rank>198</Rank>
    <Name>Rayne</Name>
    <XpEarned>47160</XpEarned>
  </Player>
  <Player>
    <Rank>199</Rank>
    <Name>Gengsz</Name>
    <XpEarned>39050</XpEarned>
  </Player>
  <Player>
    <Rank>200</Rank>
    <Name>Drakangel</Name>
    <XpEarned>37480</XpEarned>
  </Player>
  <Player>
    <Rank>201</Rank>
    <Name>Iorshine</Name>
    <XpEarned>31523</XpEarned>
  </Player>
  <Player>
    <Rank>202</Rank>
    <Name>Dedi</Name>
    <XpEarned>13500</XpEarned>
  </Player>
  <Player>
    <Rank>203</Rank>
    <Name>Tempestad</Name>
    <XpEarned>13500</XpEarned>
  </Player>
  <Player>
    <Rank>204</Rank>
    <Name>Trapaceiro</Name>
    <XpEarned>9574</XpEarned>
  </Player>
  <Player>
    <Rank>205</Rank>
    <Name>Michael</Name>
    <XpEarned>389</XpEarned>
  </Player>
  <Player>
    <Rank>206</Rank>
    <Name>Ahyeon</Name>
    <XpEarned>90</XpEarned>
  </Player>
  <Player>
    <Rank>207</Rank>
    <Name>Game</Name>
    <XpEarned>0</XpEarned>
  </Player>
  <Player>
    <Rank>208</Rank>
    <Name>Supy</Name>
    <XpEarned>0</XpEarned>
  </Player>
  <Player>
    <Rank>209</Rank>
    <Name>Fiolu</Name>
    <XpEarned>0</XpEarned>
  </Player>
  <Player>
    <Rank>210</Rank>
    <Name>Bucca</Name>
    <XpEarned>0</XpEarned>
  </Player>
  <Player>
    <Rank>211</Rank>
    <Name>Crystal</Name>
    <XpEarned>0</XpEarned>
  </Player>
  <Player>
    <Rank>212</Rank>
    <Name>Foreskin</Name>
    <XpEarned>0</XpEarned>
  </Player>
  <Player>
    <Rank>213</Rank>
    <Name>Renegado</Name>
    <XpEarned>0</XpEarned>
  </Player>
  <Player>
    <Rank>214</Rank>
    <Name>Brokazee</Name>
    <XpEarned>0</XpEarned>
  </Player>
  <Player>
    <Rank>215</Rank>
    <Name>Reidelas</Name>
    <XpEarned>0</XpEarned>
  </Player>
  <Player>
    <Rank>216</Rank>
    <Name>Vendendo</Name>
    <XpEarned>0</XpEarned>
  </Player>
  <Player>
    <Rank>217</Rank>
    <Name>Treizoitao</Name>
    <XpEarned>0</XpEarned>
  </Player>
  <Player>
    <Rank>218</Rank>
    <Name>Magrinpjl</Name>
    <XpEarned>0</XpEarned>
  </Player>
  <Player>
    <Rank>219</Rank>
    <Name>Borala</Name>
    <XpEarned>0</XpEarned>
  </Player>
  <Player>
    <Rank>220</Rank>
    <Name>Sentinela</Name>
    <XpEarned>0</XpEarned>
  </Player>
  <Player>
    <Rank>221</Rank>
    <Name>Carnage</Name>
    <XpEarned>0</XpEarned>
  </Player>
  <Player>
    <Rank>222</Rank>
    <Name>Cochilobr</Name>
    <XpEarned>0</XpEarned>
  </Player>
  <Player>
    <Rank>223</Rank>
    <Name>Habibi</Name>
    <XpEarned>-15918762</XpEarned>
  </Player>
  <Player>
    <Rank>224</Rank>
    <Name>Brisadeira</Name>
    <XpEarned>-124328082</XpEarned>
  </Player>
</DailyXpHighscores>
