<?xml version="1.0" encoding="UTF-8"?>
<DailyXpHighscores>
  <GeneratedAt>1750041607126</GeneratedAt>
  <Player>
    <Rank>1</Rank>
    <Name>Exist</Name>
    <XpEarned>614441638</XpEarned>
  </Player>
  <Player>
    <Rank>2</Rank>
    <Name>Saskeh</Name>
    <XpEarned>470812001</XpEarned>
  </Player>
  <Player>
    <Rank>3</Rank>
    <Name>Mii</Name>
    <XpEarned>444354222</XpEarned>
  </Player>
  <Player>
    <Rank>4</Rank>
    <Name>Victorbr</Name>
    <XpEarned>426025769</XpEarned>
  </Player>
  <Player>
    <Rank>5</Rank>
    <Name>Dom</Name>
    <XpEarned>396868400</XpEarned>
  </Player>
  <Player>
    <Rank>6</Rank>
    <Name>Maxx</Name>
    <XpEarned>388170753</XpEarned>
  </Player>
  <Player>
    <Rank>7</Rank>
    <Name>Kannisword</Name>
    <XpEarned>368312562</XpEarned>
  </Player>
  <Player>
    <Rank>8</Rank>
    <Name>Wk</Name>
    <XpEarned>335723220</XpEarned>
  </Player>
  <Player>
    <Rank>9</Rank>
    <Name>Hiroshi</Name>
    <XpEarned>314943446</XpEarned>
  </Player>
  <Player>
    <Rank>10</Rank>
    <Name>Datubiadap</Name>
    <XpEarned>310913820</XpEarned>
  </Player>
  <Player>
    <Rank>11</Rank>
    <Name>Kibo</Name>
    <XpEarned>302985050</XpEarned>
  </Player>
  <Player>
    <Rank>12</Rank>
    <Name>Kannibalz</Name>
    <XpEarned>276306587</XpEarned>
  </Player>
  <Player>
    <Rank>13</Rank>
    <Name>Hawkeyez</Name>
    <XpEarned>269373452</XpEarned>
  </Player>
  <Player>
    <Rank>14</Rank>
    <Name>Digdin</Name>
    <XpEarned>267353582</XpEarned>
  </Player>
  <Player>
    <Rank>15</Rank>
    <Name>Gaspar</Name>
    <XpEarned>266614740</XpEarned>
  </Player>
  <Player>
    <Rank>16</Rank>
    <Name>Ashura</Name>
    <XpEarned>262829582</XpEarned>
  </Player>
  <Player>
    <Rank>17</Rank>
    <Name>Pintoral</Name>
    <XpEarned>255485169</XpEarned>
  </Player>
  <Player>
    <Rank>18</Rank>
    <Name>Kingdeus</Name>
    <XpEarned>254284380</XpEarned>
  </Player>
  <Player>
    <Rank>19</Rank>
    <Name>Kingkiller</Name>
    <XpEarned>249435763</XpEarned>
  </Player>
  <Player>
    <Rank>20</Rank>
    <Name>Pancernik</Name>
    <XpEarned>244384119</XpEarned>
  </Player>
  <Player>
    <Rank>21</Rank>
    <Name>Gasparwiz</Name>
    <XpEarned>230517033</XpEarned>
  </Player>
  <Player>
    <Rank>22</Rank>
    <Name>Kakashi</Name>
    <XpEarned>227263018</XpEarned>
  </Player>
  <Player>
    <Rank>23</Rank>
    <Name>Victorwiz</Name>
    <XpEarned>215003621</XpEarned>
  </Player>
  <Player>
    <Rank>24</Rank>
    <Name>Hamura</Name>
    <XpEarned>206238060</XpEarned>
  </Player>
  <Player>
    <Rank>25</Rank>
    <Name>Piras</Name>
    <XpEarned>203139077</XpEarned>
  </Player>
  <Player>
    <Rank>26</Rank>
    <Name>Niggawiz</Name>
    <XpEarned>199672717</XpEarned>
  </Player>
  <Player>
    <Rank>27</Rank>
    <Name>Mitt</Name>
    <XpEarned>192768198</XpEarned>
  </Player>
  <Player>
    <Rank>28</Rank>
    <Name>Serizawa</Name>
    <XpEarned>190870436</XpEarned>
  </Player>
  <Player>
    <Rank>29</Rank>
    <Name>Over</Name>
    <XpEarned>188545140</XpEarned>
  </Player>
  <Player>
    <Rank>30</Rank>
    <Name>Vamplod</Name>
    <XpEarned>186556863</XpEarned>
  </Player>
  <Player>
    <Rank>31</Rank>
    <Name>Papito</Name>
    <XpEarned>185205150</XpEarned>
  </Player>
  <Player>
    <Rank>32</Rank>
    <Name>Yoshikazu</Name>
    <XpEarned>176918972</XpEarned>
  </Player>
  <Player>
    <Rank>33</Rank>
    <Name>Buca</Name>
    <XpEarned>168113074</XpEarned>
  </Player>
  <Player>
    <Rank>34</Rank>
    <Name>Cupy</Name>
    <XpEarned>165043291</XpEarned>
  </Player>
  <Player>
    <Rank>35</Rank>
    <Name>Tsuyoshi</Name>
    <XpEarned>152036841</XpEarned>
  </Player>
  <Player>
    <Rank>36</Rank>
    <Name>Zed</Name>
    <XpEarned>144501270</XpEarned>
  </Player>
  <Player>
    <Rank>37</Rank>
    <Name>Jeeje</Name>
    <XpEarned>124336886</XpEarned>
  </Player>
  <Player>
    <Rank>38</Rank>
    <Name>Hypertank</Name>
    <XpEarned>113984329</XpEarned>
  </Player>
  <Player>
    <Rank>39</Rank>
    <Name>Genji</Name>
    <XpEarned>113621410</XpEarned>
  </Player>
  <Player>
    <Rank>40</Rank>
    <Name>Warr</Name>
    <XpEarned>109067112</XpEarned>
  </Player>
  <Player>
    <Rank>41</Rank>
    <Name>Willinha </Name>
    <XpEarned>65525055</XpEarned>
  </Player>
  <Player>
    <Rank>42</Rank>
    <Name>Rog</Name>
    <XpEarned>61699608</XpEarned>
  </Player>
  <Player>
    <Rank>43</Rank>
    <Name>Joker</Name>
    <XpEarned>61549034</XpEarned>
  </Player>
  <Player>
    <Rank>44</Rank>
    <Name>Alzeta</Name>
    <XpEarned>58209337</XpEarned>
  </Player>
  <Player>
    <Rank>45</Rank>
    <Name>Castiel</Name>
    <XpEarned>57442187</XpEarned>
  </Player>
  <Player>
    <Rank>46</Rank>
    <Name>Guinny</Name>
    <XpEarned>55110479</XpEarned>
  </Player>
  <Player>
    <Rank>47</Rank>
    <Name>Justen</Name>
    <XpEarned>54501715</XpEarned>
  </Player>
  <Player>
    <Rank>48</Rank>
    <Name>Dewezz</Name>
    <XpEarned>52049417</XpEarned>
  </Player>
  <Player>
    <Rank>49</Rank>
    <Name>Pablo</Name>
    <XpEarned>47445775</XpEarned>
  </Player>
  <Player>
    <Rank>50</Rank>
    <Name>Soft</Name>
    <XpEarned>45532252</XpEarned>
  </Player>
  <Player>
    <Rank>51</Rank>
    <Name>Blindadu</Name>
    <XpEarned>45347728</XpEarned>
  </Player>
  <Player>
    <Rank>52</Rank>
    <Name>Loki</Name>
    <XpEarned>44536539</XpEarned>
  </Player>
  <Player>
    <Rank>53</Rank>
    <Name>Astreus</Name>
    <XpEarned>42373404</XpEarned>
  </Player>
  <Player>
    <Rank>54</Rank>
    <Name>Superstar</Name>
    <XpEarned>41887745</XpEarned>
  </Player>
  <Player>
    <Rank>55</Rank>
    <Name>Madara</Name>
    <XpEarned>41632887</XpEarned>
  </Player>
  <Player>
    <Rank>56</Rank>
    <Name>Boruto</Name>
    <XpEarned>41441877</XpEarned>
  </Player>
  <Player>
    <Rank>57</Rank>
    <Name>Bruxo</Name>
    <XpEarned>40924453</XpEarned>
  </Player>
  <Player>
    <Rank>58</Rank>
    <Name>Justin</Name>
    <XpEarned>40521526</XpEarned>
  </Player>
  <Player>
    <Rank>59</Rank>
    <Name>Rigger</Name>
    <XpEarned>40084128</XpEarned>
  </Player>
  <Player>
    <Rank>60</Rank>
    <Name>Dyvnee</Name>
    <XpEarned>38109427</XpEarned>
  </Player>
  <Player>
    <Rank>61</Rank>
    <Name>Powerofgod</Name>
    <XpEarned>37845360</XpEarned>
  </Player>
  <Player>
    <Rank>62</Rank>
    <Name>Zeboostin</Name>
    <XpEarned>37616607</XpEarned>
  </Player>
  <Player>
    <Rank>63</Rank>
    <Name>Kannizinha</Name>
    <XpEarned>34706437</XpEarned>
  </Player>
  <Player>
    <Rank>64</Rank>
    <Name>Gandalf</Name>
    <XpEarned>34613419</XpEarned>
  </Player>
  <Player>
    <Rank>65</Rank>
    <Name>Lordblack</Name>
    <XpEarned>34322817</XpEarned>
  </Player>
  <Player>
    <Rank>66</Rank>
    <Name>Rokz</Name>
    <XpEarned>33694327</XpEarned>
  </Player>
  <Player>
    <Rank>67</Rank>
    <Name>Piraswiz</Name>
    <XpEarned>32932729</XpEarned>
  </Player>
  <Player>
    <Rank>68</Rank>
    <Name>Eunha</Name>
    <XpEarned>32266976</XpEarned>
  </Player>
  <Player>
    <Rank>69</Rank>
    <Name>Pageone</Name>
    <XpEarned>31942940</XpEarned>
  </Player>
  <Player>
    <Rank>70</Rank>
    <Name>Scott</Name>
    <XpEarned>31583464</XpEarned>
  </Player>
  <Player>
    <Rank>71</Rank>
    <Name>Terrifier</Name>
    <XpEarned>29738059</XpEarned>
  </Player>
  <Player>
    <Rank>72</Rank>
    <Name>Panqueca </Name>
    <XpEarned>29713959</XpEarned>
  </Player>
  <Player>
    <Rank>73</Rank>
    <Name>Pandatank</Name>
    <XpEarned>27740947</XpEarned>
  </Player>
  <Player>
    <Rank>74</Rank>
    <Name>Belzebugod</Name>
    <XpEarned>27674724</XpEarned>
  </Player>
  <Player>
    <Rank>75</Rank>
    <Name>Movie</Name>
    <XpEarned>26497277</XpEarned>
  </Player>
  <Player>
    <Rank>76</Rank>
    <Name>Hellokitty</Name>
    <XpEarned>26261971</XpEarned>
  </Player>
  <Player>
    <Rank>77</Rank>
    <Name>Mit</Name>
    <XpEarned>25469950</XpEarned>
  </Player>
  <Player>
    <Rank>78</Rank>
    <Name>Mi</Name>
    <XpEarned>25363139</XpEarned>
  </Player>
  <Player>
    <Rank>79</Rank>
    <Name>Seis</Name>
    <XpEarned>20789585</XpEarned>
  </Player>
  <Player>
    <Rank>80</Rank>
    <Name>Wizze</Name>
    <XpEarned>20729520</XpEarned>
  </Player>
  <Player>
    <Rank>81</Rank>
    <Name>Goldtanker</Name>
    <XpEarned>20550689</XpEarned>
  </Player>
  <Player>
    <Rank>82</Rank>
    <Name>Megume</Name>
    <XpEarned>19944958</XpEarned>
  </Player>
  <Player>
    <Rank>83</Rank>
    <Name>Enio</Name>
    <XpEarned>19457003</XpEarned>
  </Player>
  <Player>
    <Rank>84</Rank>
    <Name>Destino</Name>
    <XpEarned>18565438</XpEarned>
  </Player>
  <Player>
    <Rank>85</Rank>
    <Name>Giovani</Name>
    <XpEarned>18203034</XpEarned>
  </Player>
  <Player>
    <Rank>86</Rank>
    <Name>Lendario</Name>
    <XpEarned>17669514</XpEarned>
  </Player>
  <Player>
    <Rank>87</Rank>
    <Name>Kanki</Name>
    <XpEarned>16217298</XpEarned>
  </Player>
  <Player>
    <Rank>88</Rank>
    <Name>Dark</Name>
    <XpEarned>16138689</XpEarned>
  </Player>
  <Player>
    <Rank>89</Rank>
    <Name>Cinco</Name>
    <XpEarned>15732191</XpEarned>
  </Player>
  <Player>
    <Rank>90</Rank>
    <Name>Stella</Name>
    <XpEarned>15634639</XpEarned>
  </Player>
  <Player>
    <Rank>91</Rank>
    <Name>Rei</Name>
    <XpEarned>15597691</XpEarned>
  </Player>
  <Player>
    <Rank>92</Rank>
    <Name>Panda</Name>
    <XpEarned>15573344</XpEarned>
  </Player>
  <Player>
    <Rank>93</Rank>
    <Name>Magicol</Name>
    <XpEarned>15273638</XpEarned>
  </Player>
  <Player>
    <Rank>94</Rank>
    <Name>Trovao</Name>
    <XpEarned>15116273</XpEarned>
  </Player>
  <Player>
    <Rank>95</Rank>
    <Name>Quatro</Name>
    <XpEarned>15027243</XpEarned>
  </Player>
  <Player>
    <Rank>96</Rank>
    <Name>Blindada</Name>
    <XpEarned>14891560</XpEarned>
  </Player>
  <Player>
    <Rank>97</Rank>
    <Name>Wizzard</Name>
    <XpEarned>14767840</XpEarned>
  </Player>
  <Player>
    <Rank>98</Rank>
    <Name>Blindado</Name>
    <XpEarned>14660645</XpEarned>
  </Player>
  <Player>
    <Rank>99</Rank>
    <Name>Vegapunk</Name>
    <XpEarned>13724632</XpEarned>
  </Player>
  <Player>
    <Rank>100</Rank>
    <Name>Eloa</Name>
    <XpEarned>13700686</XpEarned>
  </Player>
  <Player>
    <Rank>101</Rank>
    <Name>Dblack</Name>
    <XpEarned>13369568</XpEarned>
  </Player>
  <Player>
    <Rank>102</Rank>
    <Name>Bebelaq</Name>
    <XpEarned>13335292</XpEarned>
  </Player>
  <Player>
    <Rank>103</Rank>
    <Name>Dewez</Name>
    <XpEarned>12794550</XpEarned>
  </Player>
  <Player>
    <Rank>104</Rank>
    <Name>Hakina</Name>
    <XpEarned>12557581</XpEarned>
  </Player>
  <Player>
    <Rank>105</Rank>
    <Name>Lorded</Name>
    <XpEarned>12285000</XpEarned>
  </Player>
  <Player>
    <Rank>106</Rank>
    <Name>Raphaooo</Name>
    <XpEarned>11786527</XpEarned>
  </Player>
  <Player>
    <Rank>107</Rank>
    <Name>Reheli</Name>
    <XpEarned>11644560</XpEarned>
  </Player>
  <Player>
    <Rank>108</Rank>
    <Name>Goldwiz</Name>
    <XpEarned>11022573</XpEarned>
  </Player>
  <Player>
    <Rank>109</Rank>
    <Name>Talrok</Name>
    <XpEarned>10818874</XpEarned>
  </Player>
  <Player>
    <Rank>110</Rank>
    <Name>Killer</Name>
    <XpEarned>10561191</XpEarned>
  </Player>
  <Player>
    <Rank>111</Rank>
    <Name>Guard</Name>
    <XpEarned>10438596</XpEarned>
  </Player>
  <Player>
    <Rank>112</Rank>
    <Name>Gacorrr</Name>
    <XpEarned>9987613</XpEarned>
  </Player>
  <Player>
    <Rank>113</Rank>
    <Name>Magezin</Name>
    <XpEarned>9972000</XpEarned>
  </Player>
  <Player>
    <Rank>114</Rank>
    <Name>Quebeck</Name>
    <XpEarned>9652446</XpEarned>
  </Player>
  <Player>
    <Rank>115</Rank>
    <Name>Zhouzinn</Name>
    <XpEarned>9612000</XpEarned>
  </Player>
  <Player>
    <Rank>116</Rank>
    <Name>Goldwizz</Name>
    <XpEarned>9349200</XpEarned>
  </Player>
  <Player>
    <Rank>117</Rank>
    <Name>Panqueca</Name>
    <XpEarned>9188773</XpEarned>
  </Player>
  <Player>
    <Rank>118</Rank>
    <Name>Redeon</Name>
    <XpEarned>8972437</XpEarned>
  </Player>
  <Player>
    <Rank>119</Rank>
    <Name>Blindao</Name>
    <XpEarned>8814993</XpEarned>
  </Player>
  <Player>
    <Rank>120</Rank>
    <Name>Redzin</Name>
    <XpEarned>8675100</XpEarned>
  </Player>
  <Player>
    <Rank>121</Rank>
    <Name>Goldwizzz</Name>
    <XpEarned>8082697</XpEarned>
  </Player>
  <Player>
    <Rank>122</Rank>
    <Name>Nauk</Name>
    <XpEarned>7957091</XpEarned>
  </Player>
  <Player>
    <Rank>123</Rank>
    <Name>Ghost</Name>
    <XpEarned>7667118</XpEarned>
  </Player>
  <Player>
    <Rank>124</Rank>
    <Name>Galadriel</Name>
    <XpEarned>7341445</XpEarned>
  </Player>
  <Player>
    <Rank>125</Rank>
    <Name>Tec</Name>
    <XpEarned>7071705</XpEarned>
  </Player>
  <Player>
    <Rank>126</Rank>
    <Name>Killerwiz</Name>
    <XpEarned>6478353</XpEarned>
  </Player>
  <Player>
    <Rank>127</Rank>
    <Name>Matadordpk</Name>
    <XpEarned>6435000</XpEarned>
  </Player>
  <Player>
    <Rank>128</Rank>
    <Name>Shaog</Name>
    <XpEarned>6331256</XpEarned>
  </Player>
  <Player>
    <Rank>129</Rank>
    <Name>Nena</Name>
    <XpEarned>6201623</XpEarned>
  </Player>
  <Player>
    <Rank>130</Rank>
    <Name>Riquekmila</Name>
    <XpEarned>6173806</XpEarned>
  </Player>
  <Player>
    <Rank>131</Rank>
    <Name>Exor</Name>
    <XpEarned>6113223</XpEarned>
  </Player>
  <Player>
    <Rank>132</Rank>
    <Name>Knight</Name>
    <XpEarned>6044853</XpEarned>
  </Player>
  <Player>
    <Rank>133</Rank>
    <Name>Ravena</Name>
    <XpEarned>5904446</XpEarned>
  </Player>
  <Player>
    <Rank>134</Rank>
    <Name>Kratos</Name>
    <XpEarned>5495850</XpEarned>
  </Player>
  <Player>
    <Rank>135</Rank>
    <Name>Emilia</Name>
    <XpEarned>4998973</XpEarned>
  </Player>
  <Player>
    <Rank>136</Rank>
    <Name>Ganny</Name>
    <XpEarned>4453370</XpEarned>
  </Player>
  <Player>
    <Rank>137</Rank>
    <Name>Templarr</Name>
    <XpEarned>4453300</XpEarned>
  </Player>
  <Player>
    <Rank>138</Rank>
    <Name>Borutos</Name>
    <XpEarned>4053997</XpEarned>
  </Player>
  <Player>
    <Rank>139</Rank>
    <Name>Game</Name>
    <XpEarned>3311573</XpEarned>
  </Player>
  <Player>
    <Rank>140</Rank>
    <Name>Nenawiz</Name>
    <XpEarned>3131965</XpEarned>
  </Player>
  <Player>
    <Rank>141</Rank>
    <Name>Shadowww</Name>
    <XpEarned>2933335</XpEarned>
  </Player>
  <Player>
    <Rank>142</Rank>
    <Name>Babydoll</Name>
    <XpEarned>2827659</XpEarned>
  </Player>
  <Player>
    <Rank>143</Rank>
    <Name>Supy</Name>
    <XpEarned>2699554</XpEarned>
  </Player>
  <Player>
    <Rank>144</Rank>
    <Name>Liontin</Name>
    <XpEarned>2623449</XpEarned>
  </Player>
  <Player>
    <Rank>145</Rank>
    <Name>Dragonbr</Name>
    <XpEarned>2595349</XpEarned>
  </Player>
  <Player>
    <Rank>146</Rank>
    <Name>Noia</Name>
    <XpEarned>2433961</XpEarned>
  </Player>
  <Player>
    <Rank>147</Rank>
    <Name>Sakura</Name>
    <XpEarned>2390525</XpEarned>
  </Player>
  <Player>
    <Rank>148</Rank>
    <Name>Dexterr</Name>
    <XpEarned>2319759</XpEarned>
  </Player>
  <Player>
    <Rank>149</Rank>
    <Name>Binance</Name>
    <XpEarned>2311576</XpEarned>
  </Player>
  <Player>
    <Rank>150</Rank>
    <Name>Bonilha</Name>
    <XpEarned>2225250</XpEarned>
  </Player>
  <Player>
    <Rank>151</Rank>
    <Name>Tuyull</Name>
    <XpEarned>2039855</XpEarned>
  </Player>
  <Player>
    <Rank>152</Rank>
    <Name>Hellwilzz</Name>
    <XpEarned>1992707</XpEarned>
  </Player>
  <Player>
    <Rank>153</Rank>
    <Name>Qiu</Name>
    <XpEarned>1976850</XpEarned>
  </Player>
  <Player>
    <Rank>154</Rank>
    <Name>Papeka</Name>
    <XpEarned>1900000</XpEarned>
  </Player>
  <Player>
    <Rank>155</Rank>
    <Name>Demonio </Name>
    <XpEarned>1895549</XpEarned>
  </Player>
  <Player>
    <Rank>156</Rank>
    <Name>Durin</Name>
    <XpEarned>1735452</XpEarned>
  </Player>
  <Player>
    <Rank>157</Rank>
    <Name>Bucca</Name>
    <XpEarned>1555463</XpEarned>
  </Player>
  <Player>
    <Rank>158</Rank>
    <Name>Poppay</Name>
    <XpEarned>1425540</XpEarned>
  </Player>
  <Player>
    <Rank>159</Rank>
    <Name>Bsm</Name>
    <XpEarned>1425198</XpEarned>
  </Player>
  <Player>
    <Rank>160</Rank>
    <Name>Salamaleko</Name>
    <XpEarned>1425000</XpEarned>
  </Player>
  <Player>
    <Rank>161</Rank>
    <Name>Alegria</Name>
    <XpEarned>1425000</XpEarned>
  </Player>
  <Player>
    <Rank>162</Rank>
    <Name>Malekosala</Name>
    <XpEarned>1425000</XpEarned>
  </Player>
  <Player>
    <Rank>163</Rank>
    <Name>Mihawk</Name>
    <XpEarned>1351691</XpEarned>
  </Player>
  <Player>
    <Rank>164</Rank>
    <Name>Fiolu</Name>
    <XpEarned>1283816</XpEarned>
  </Player>
  <Player>
    <Rank>165</Rank>
    <Name>Kelavan</Name>
    <XpEarned>1247486</XpEarned>
  </Player>
  <Player>
    <Rank>166</Rank>
    <Name>Mitth</Name>
    <XpEarned>996575</XpEarned>
  </Player>
  <Player>
    <Rank>167</Rank>
    <Name>Pablinhu</Name>
    <XpEarned>995078</XpEarned>
  </Player>
  <Player>
    <Rank>168</Rank>
    <Name>Cochilo</Name>
    <XpEarned>991490</XpEarned>
  </Player>
  <Player>
    <Rank>169</Rank>
    <Name>Khorhigee</Name>
    <XpEarned>979812</XpEarned>
  </Player>
  <Player>
    <Rank>170</Rank>
    <Name>Dinastia</Name>
    <XpEarned>968242</XpEarned>
  </Player>
  <Player>
    <Rank>171</Rank>
    <Name>Oneto</Name>
    <XpEarned>950000</XpEarned>
  </Player>
  <Player>
    <Rank>172</Rank>
    <Name>Baby</Name>
    <XpEarned>950000</XpEarned>
  </Player>
  <Player>
    <Rank>173</Rank>
    <Name>Euvelia</Name>
    <XpEarned>950000</XpEarned>
  </Player>
  <Player>
    <Rank>174</Rank>
    <Name>Dexterwiz</Name>
    <XpEarned>876960</XpEarned>
  </Player>
  <Player>
    <Rank>175</Rank>
    <Name>Fzkeblorcr</Name>
    <XpEarned>832977</XpEarned>
  </Player>
  <Player>
    <Rank>176</Rank>
    <Name>Valkiria</Name>
    <XpEarned>823680</XpEarned>
  </Player>
  <Player>
    <Rank>177</Rank>
    <Name>Dhidy</Name>
    <XpEarned>696514</XpEarned>
  </Player>
  <Player>
    <Rank>178</Rank>
    <Name>Cedric</Name>
    <XpEarned>659848</XpEarned>
  </Player>
  <Player>
    <Rank>179</Rank>
    <Name>Khun</Name>
    <XpEarned>658827</XpEarned>
  </Player>
  <Player>
    <Rank>180</Rank>
    <Name>Dewes</Name>
    <XpEarned>650718</XpEarned>
  </Player>
  <Player>
    <Rank>181</Rank>
    <Name>Liliks</Name>
    <XpEarned>589973</XpEarned>
  </Player>
  <Player>
    <Rank>182</Rank>
    <Name>Jembuff</Name>
    <XpEarned>503167</XpEarned>
  </Player>
  <Player>
    <Rank>183</Rank>
    <Name>Niggawar</Name>
    <XpEarned>499581</XpEarned>
  </Player>
  <Player>
    <Rank>184</Rank>
    <Name>Srlira</Name>
    <XpEarned>469516</XpEarned>
  </Player>
  <Player>
    <Rank>185</Rank>
    <Name>Kaparzo</Name>
    <XpEarned>464417</XpEarned>
  </Player>
  <Player>
    <Rank>186</Rank>
    <Name>Kannivrau</Name>
    <XpEarned>429166</XpEarned>
  </Player>
  <Player>
    <Rank>187</Rank>
    <Name>Troyn</Name>
    <XpEarned>393573</XpEarned>
  </Player>
  <Player>
    <Rank>188</Rank>
    <Name>Vandamez</Name>
    <XpEarned>338369</XpEarned>
  </Player>
  <Player>
    <Rank>189</Rank>
    <Name>Kaisel</Name>
    <XpEarned>279929</XpEarned>
  </Player>
  <Player>
    <Rank>190</Rank>
    <Name>Verockx</Name>
    <XpEarned>252954</XpEarned>
  </Player>
  <Player>
    <Rank>191</Rank>
    <Name>Lordwolf </Name>
    <XpEarned>229537</XpEarned>
  </Player>
  <Player>
    <Rank>192</Rank>
    <Name>Skyrim</Name>
    <XpEarned>228464</XpEarned>
  </Player>
  <Player>
    <Rank>193</Rank>
    <Name>Somnus</Name>
    <XpEarned>194312</XpEarned>
  </Player>
  <Player>
    <Rank>194</Rank>
    <Name>Sxgabrielx</Name>
    <XpEarned>185640</XpEarned>
  </Player>
  <Player>
    <Rank>195</Rank>
    <Name>Heineken</Name>
    <XpEarned>156521</XpEarned>
  </Player>
  <Player>
    <Rank>196</Rank>
    <Name>Laubisomi </Name>
    <XpEarned>145989</XpEarned>
  </Player>
  <Player>
    <Rank>197</Rank>
    <Name>Crydevilz</Name>
    <XpEarned>141610</XpEarned>
  </Player>
  <Player>
    <Rank>198</Rank>
    <Name>Lith</Name>
    <XpEarned>141144</XpEarned>
  </Player>
  <Player>
    <Rank>199</Rank>
    <Name>Mrdoman</Name>
    <XpEarned>125141</XpEarned>
  </Player>
  <Player>
    <Rank>200</Rank>
    <Name>Maciano</Name>
    <XpEarned>74604</XpEarned>
  </Player>
  <Player>
    <Rank>201</Rank>
    <Name>Melkor</Name>
    <XpEarned>71190</XpEarned>
  </Player>
  <Player>
    <Rank>202</Rank>
    <Name>Lessako</Name>
    <XpEarned>55686</XpEarned>
  </Player>
  <Player>
    <Rank>203</Rank>
    <Name>Moondeath</Name>
    <XpEarned>49770</XpEarned>
  </Player>
  <Player>
    <Rank>204</Rank>
    <Name>Drink</Name>
    <XpEarned>37512</XpEarned>
  </Player>
  <Player>
    <Rank>205</Rank>
    <Name>Vulion</Name>
    <XpEarned>27589</XpEarned>
  </Player>
  <Player>
    <Rank>206</Rank>
    <Name>Suri</Name>
    <XpEarned>25095</XpEarned>
  </Player>
  <Player>
    <Rank>207</Rank>
    <Name>Feiticeira</Name>
    <XpEarned>24300</XpEarned>
  </Player>
  <Player>
    <Rank>208</Rank>
    <Name>Nalen</Name>
    <XpEarned>13122</XpEarned>
  </Player>
  <Player>
    <Rank>209</Rank>
    <Name>Dressrossa</Name>
    <XpEarned>7820</XpEarned>
  </Player>
  <Player>
    <Rank>210</Rank>
    <Name>And</Name>
    <XpEarned>3597</XpEarned>
  </Player>
  <Player>
    <Rank>211</Rank>
    <Name>Otto</Name>
    <XpEarned>3195</XpEarned>
  </Player>
  <Player>
    <Rank>212</Rank>
    <Name>Kant</Name>
    <XpEarned>2655</XpEarned>
  </Player>
  <Player>
    <Rank>213</Rank>
    <Name>Omadara</Name>
    <XpEarned>776</XpEarned>
  </Player>
  <Player>
    <Rank>214</Rank>
    <Name>Iorshine </Name>
    <XpEarned>0</XpEarned>
  </Player>
  <Player>
    <Rank>215</Rank>
    <Name>Renegado</Name>
    <XpEarned>0</XpEarned>
  </Player>
  <Player>
    <Rank>216</Rank>
    <Name>Reidelas</Name>
    <XpEarned>0</XpEarned>
  </Player>
  <Player>
    <Rank>217</Rank>
    <Name>Borala</Name>
    <XpEarned>0</XpEarned>
  </Player>
  <Player>
    <Rank>218</Rank>
    <Name>Punipun</Name>
    <XpEarned>0</XpEarned>
  </Player>
  <Player>
    <Rank>219</Rank>
    <Name>Lupy</Name>
    <XpEarned>0</XpEarned>
  </Player>
  <Player>
    <Rank>220</Rank>
    <Name>Sandra</Name>
    <XpEarned>0</XpEarned>
  </Player>
  <Player>
    <Rank>221</Rank>
    <Name>Neon</Name>
    <XpEarned>-4110411</XpEarned>
  </Player>
  <Player>
    <Rank>222</Rank>
    <Name>Zin</Name>
    <XpEarned>-15135378</XpEarned>
  </Player>
</DailyXpHighscores>
